Workbook

Sheet 流水记账
A1: 日期 | B1: 星期 | C1: 分类 | D1: 事项 | E1: 详情 | F1: 支出金额 | G1: 收入金额 | H1: 当笔净额 | I1: 支付方式 | J1: 备注
A2: 2026年1月｜第一周（1月1日 - 1月7日）
A3: 日期 | B3: 星期 | C3: 分类 | D3: 事项 | E3: 详情 | F3: 支出金额 | G3: 收入金额 | H3: 当笔净额 | I3: 支付方式 | J3: 备注
A4: 46023 | B4: 星期四 | C4: 餐饮 | D4: 早餐 | H4: =IF(AND(F4="",G4=""),"",G4-F4)
A5: 46023 | B5: 星期四 | C5: 餐饮 | D5: 中餐 | H5: =IF(AND(F5="",G5=""),"",G5-F5)
A6: 46023 | B6: 星期四 | C6: 餐饮 | D6: 晚餐 | H6: =IF(AND(F6="",G6=""),"",G6-F6)
A7: 46023 | B7: 星期四 | C7: 奶茶/咖啡 | D7: 奶茶/咖啡 | H7: =IF(AND(F7="",G7=""),"",G7-F7)
A8: 46023 | B8: 星期四 | C8: 其他 | D8: 其他 | H8: =IF(AND(F8="",G8=""),"",G8-F8)
A9: 46023 | B9: 星期四 | C9: 其他 | D9: 其他 | H9: =IF(AND(F9="",G9=""),"",G9-F9)
A10: 46024 | B10: 星期五 | C10: 餐饮 | D10: 早餐 | H10: =IF(AND(F10="",G10=""),"",G10-F10)
A11: 46024 | B11: 星期五 | C11: 餐饮 | D11: 中餐 | H11: =IF(AND(F11="",G11=""),"",G11-F11)
A12: 46024 | B12: 星期五 | C12: 餐饮 | D12: 晚餐 | H12: =IF(AND(F12="",G12=""),"",G12-F12)
A13: 46024 | B13: 星期五 | C13: 奶茶/咖啡 | D13: 奶茶/咖啡 | H13: =IF(AND(F13="",G13=""),"",G13-F13)
A14: 46024 | B14: 星期五 | C14: 其他 | D14: 其他 | H14: =IF(AND(F14="",G14=""),"",G14-F14)
A15: 46024 | B15: 星期五 | C15: 其他 | D15: 其他 | H15: =IF(AND(F15="",G15=""),"",G15-F15)
... A45: 46029 | B45: 星期三 | C45: 其他 | D45: 其他 | H45: =IF(AND(F45="",G45=""),"",G45-F45)
A46: 本周小计 | F46: =SUMIFS($F:$F,$A:$A,">="&DATE(2026,1,1),$A:$A,"<="&DATE(2026,1,7)) | G46: =SUMIFS($G:$G,$A:$A,">="&DATE(2026,1,1),$A:$A,"<="&DATE(2026,1,7)) | H46: =G46-F46
A49: 2026年1月｜第二周（1月8日 - 1月14日）
A50: 日期 | B50: 星期 | C50: 分类 | D50: 事项 | E50: 详情 | F50: 支出金额 | G50: 收入金额 | H50: 当笔净额 | I50: 支付方式 | J50: 备注
A51: 46030 | B51: 星期四 | C51: 餐饮 | D51: 早餐 | H51: =IF(AND(F51="",G51=""),"",G51-F51)
A52: 46030 | B52: 星期四 | C52: 餐饮 | D52: 中餐 | H52: =IF(AND(F52="",G52=""),"",G52-F52)
A53: 46030 | B53: 星期四 | C53: 餐饮 | D53: 晚餐 | H53: =IF(AND(F53="",G53=""),"",G53-F53)
A54: 46030 | B54: 星期四 | C54: 奶茶/咖啡 | D54: 奶茶/咖啡 | H54: =IF(AND(F54="",G54=""),"",G54-F54)
A55: 46030 | B55: 星期四 | C55: 其他 | D55: 其他 | H55: =IF(AND(F55="",G55=""),"",G55-F55)
A56: 46030 | B56: 星期四 | C56: 其他 | D56: 其他 | H56: =IF(AND(F56="",G56=""),"",G56-F56)
A57: 46031 | B57: 星期五 | C57: 餐饮 | D57: 早餐 | H57: =IF(AND(F57="",G57=""),"",G57-F57)
A58: 46031 | B58: 星期五 | C58: 餐饮 | D58: 中餐 | H58: =IF(AND(F58="",G58=""),"",G58-F58)
A59: 46031 | B59: 星期五 | C59: 餐饮 | D59: 晚餐 | H59: =IF(AND(F59="",G59=""),"",G59-F59)
A60: 46031 | B60: 星期五 | C60: 奶茶/咖啡 | D60: 奶茶/咖啡 | H60: =IF(AND(F60="",G60=""),"",G60-F60)
A61: 46031 | B61: 星期五 | C61: 其他 | D61: 其他 | H61: =IF(AND(F61="",G61=""),"",G61-F61)
A62: 46031 | B62: 星期五 | C62: 其他 | D62: 其他 | H62: =IF(AND(F62="",G62=""),"",G62-F62)
... A92: 46036 | B92: 星期三 | C92: 其他 | D92: 其他 | H92: =IF(AND(F92="",G92=""),"",G92-F92)
A93: 本周小计 | F93: =SUMIFS($F:$F,$A:$A,">="&DATE(2026,1,8),$A:$A,"<="&DATE(2026,1,14)) | G93: =SUMIFS($G:$G,$A:$A,">="&DATE(2026,1,8),$A:$A,"<="&DATE(2026,1,14)) | H93: =G93-F93
A96: 2026年1月｜第三周（1月15日 - 1月21日）
A97: 日期 | B97: 星期 | C97: 分类 | D97: 事项 | E97: 详情 | F97: 支出金额 | G97: 收入金额 | H97: 当笔净额 | I97: 支付方式 | J97: 备注
A98: 46037 | B98: 星期四 | C98: 餐饮 | D98: 早餐 | H98: =IF(AND(F98="",G98=""),"",G98-F98)
A99: 46037 | B99: 星期四 | C99: 餐饮 | D99: 中餐 | H99: =IF(AND(F99="",G99=""),"",G99-F99)
A100: 46037 | B100: 星期四 | C100: 餐饮 | D100: 晚餐 | H100: =IF(AND(F100="",G100=""),"",G100-F100)
A101: 46037 | B101: 星期四 | C101: 奶茶/咖啡 | D101: 奶茶/咖啡 | H101: =IF(AND(F101="",G101=""),"",G101-F101)
A102: 46037 | B102: 星期四 | C102: 其他 | D102: 其他 | H102: =IF(AND(F102="",G102=""),"",G102-F102)
A103: 46037 | B103: 星期四 | C103: 其他 | D103: 其他 | H103: =IF(AND(F103="",G103=""),"",G103-F103)
A104: 46038 | B104: 星期五 | C104: 餐饮 | D104: 早餐 | H104: =IF(AND(F104="",G104=""),"",G104-F104)
A105: 46038 | B105: 星期五 | C105: 餐饮 | D105: 中餐 | H105: =IF(AND(F105="",G105=""),"",G105-F105)
A106: 46038 | B106: 星期五 | C106: 餐饮 | D106: 晚餐 | H106: =IF(AND(F106="",G106=""),"",G106-F106)
A107: 46038 | B107: 星期五 | C107: 奶茶/咖啡 | D107: 奶茶/咖啡 | H107: =IF(AND(F107="",G107=""),"",G107-F107)
A108: 46038 | B108: 星期五 | C108: 其他 | D108: 其他 | H108: =IF(AND(F108="",G108=""),"",G108-F108)
A109: 46038 | B109: 星期五 | C109: 其他 | D109: 其他 | H109: =IF(AND(F109="",G109=""),"",G109-F109)
... A139: 46043 | B139: 星期三 | C139: 其他 | D139: 其他 | H139: =IF(AND(F139="",G139=""),"",G139-F139)
A140: 本周小计 | F140: =SUMIFS($F:$F,$A:$A,">="&DATE(2026,1,15),$A:$A,"<="&DATE(2026,1,21)) | G140: =SUMIFS($G:$G,$A:$A,">="&DATE(2026,1,15),$A:$A,"<="&DATE(2026,1,21)) | H140: =G140-F140
A143: 2026年1月｜第四周（1月22日 - 1月28日）
A144: 日期 | B144: 星期 | C144: 分类 | D144: 事项 | E144: 详情 | F144: 支出金额 | G144: 收入金额 | H144: 当笔净额 | I144: 支付方式 | J144: 备注
A145: 46044 | B145: 星期四 | C145: 餐饮 | D145: 早餐 | H145: =IF(AND(F145="",G145=""),"",G145-F145)
A146: 46044 | B146: 星期四 | C146: 餐饮 | D146: 中餐 | H146: =IF(AND(F146="",G146=""),"",G146-F146)
A147: 46044 | B147: 星期四 | C147: 餐饮 | D147: 晚餐 | H147: =IF(AND(F147="",G147=""),"",G147-F147)
A148: 46044 | B148: 星期四 | C148: 奶茶/咖啡 | D148: 奶茶/咖啡 | H148: =IF(AND(F148="",G148=""),"",G148-F148)
A149: 46044 | B149: 星期四 | C149: 其他 | D149: 其他 | H149: =IF(AND(F149="",G149=""),"",G149-F149)
A150: 46044 | B150: 星期四 | C150: 其他 | D150: 其他 | H150: =IF(AND(F150="",G150=""),"",G150-F150)
A151: 46045 | B151: 星期五 | C151: 餐饮 | D151: 早餐 | H151: =IF(AND(F151="",G151=""),"",G151-F151)
A152: 46045 | B152: 星期五 | C152: 餐饮 | D152: 中餐 | H152: =IF(AND(F152="",G152=""),"",G152-F152)
A153: 46045 | B153: 星期五 | C153: 餐饮 | D153: 晚餐 | H153: =IF(AND(F153="",G153=""),"",G153-F153)
A154: 46045 | B154: 星期五 | C154: 奶茶/咖啡 | D154: 奶茶/咖啡 | H154: =IF(AND(F154="",G154=""),"",G154-F154)
A155: 46045 | B155: 星期五 | C155: 其他 | D155: 其他 | H155: =IF(AND(F155="",G155=""),"",G155-F155)
A156: 46045 | B156: 星期五 | C156: 其他 | D156: 其他 | H156: =IF(AND(F156="",G156=""),"",G156-F156)
... A186: 46050 | B186: 星期三 | C186: 其他 | D186: 其他 | H186: =IF(AND(F186="",G186=""),"",G186-F186)
A187: 本周小计 | F187: =SUMIFS($F:$F,$A:$A,">="&DATE(2026,1,22),$A:$A,"<="&DATE(2026,1,28)) | G187: =SUMIFS($G:$G,$A:$A,">="&DATE(2026,1,22),$A:$A,"<="&DATE(2026,1,28)) | H187: =G187-F187
A190: 2026年1月-2月｜第五周（1月29日 - 2月4日）
A191: 日期 | B191: 星期 | C191: 分类 | D191: 事项 | E191: 详情 | F191: 支出金额 | G191: 收入金额 | H191: 当笔净额 | I191: 支付方式 | J191: 备注
A192: 46051 | B192: 星期四 | C192: 餐饮 | D192: 早餐 | H192: =IF(AND(F192="",G192=""),"",G192-F192)
A193: 46051 | B193: 星期四 | C193: 餐饮 | D193: 中餐 | H193: =IF(AND(F193="",G193=""),"",G193-F193)
A194: 46051 | B194: 星期四 | C194: 餐饮 | D194: 晚餐 | H194: =IF(AND(F194="",G194=""),"",G194-F194)
A195: 46051 | B195: 星期四 | C195: 奶茶/咖啡 | D195: 奶茶/咖啡 | H195: =IF(AND(F195="",G195=""),"",G195-F195)
A196: 46051 | B196: 星期四 | C196: 其他 | D196: 其他 | H196: =IF(AND(F196="",G196=""),"",G196-F196)
A197: 46051 | B197: 星期四 | C197: 其他 | D197: 其他 | H197: =IF(AND(F197="",G197=""),"",G197-F197)
A198: 46052 | B198: 星期五 | C198: 餐饮 | D198: 早餐 | H198: =IF(AND(F198="",G198=""),"",G198-F198)
A199: 46052 | B199: 星期五 | C199: 餐饮 | D199: 中餐 | H199: =IF(AND(F199="",G199=""),"",G199-F199)
A200: 46052 | B200: 星期五 | C200: 餐饮 | D200: 晚餐 | H200: =IF(AND(F200="",G200=""),"",G200-F200)
A201: 46052 | B201: 星期五 | C201: 奶茶/咖啡 | D201: 奶茶/咖啡 | H201: =IF(AND(F201="",G201=""),"",G201-F201)
A202: 46052 | B202: 星期五 | C202: 其他 | D202: 其他 | H202: =IF(AND(F202="",G202=""),"",G202-F202)
A203: 46052 | B203: 星期五 | C203: 其他 | D203: 其他 | H203: =IF(AND(F203="",G203=""),"",G203-F203)
... A233: 46057 | B233: 星期三 | C233: 其他 | D233: 其他 | H233: =IF(AND(F233="",G233=""),"",G233-F233)
A234: 本周小计 | F234: =SUMIFS($F:$F,$A:$A,">="&DATE(2026,1,29),$A:$A,"<="&DATE(2026,2,4)) | G234: =SUMIFS($G:$G,$A:$A,">="&DATE(2026,1,29),$A:$A,"<="&DATE(2026,2,4)) | H234: =G234-F234
A237: 2026年2月｜第一周（2月5日 - 2月11日）
A238: 日期 | B238: 星期 | C238: 分类 | D238: 事项 | E238: 详情 | F238: 支出金额 | G238: 收入金额 | H238: 当笔净额 | I238: 支付方式 | J238: 备注
A239: 46058 | B239: 星期四 | C239: 餐饮 | D239: 早餐 | H239: =IF(AND(F239="",G239=""),"",G239-F239)
A240: 46058 | B240: 星期四 | C240: 餐饮 | D240: 中餐 | H240: =IF(AND(F240="",G240=""),"",G240-F240)
A241: 46058 | B241: 星期四 | C241: 餐饮 | D241: 晚餐 | H241: =IF(AND(F241="",G241=""),"",G241-F241)
A242: 46058 | B242: 星期四 | C242: 奶茶/咖啡 | D242: 奶茶/咖啡 | H242: =IF(AND(F242="",G242=""),"",G242-F242)
A243: 46058 | B243: 星期四 | C243: 其他 | D243: 其他 | H243: =IF(AND(F243="",G243=""),"",G243-F243)
A244: 46058 | B244: 星期四 | C244: 其他 | D244: 其他 | H244: =IF(AND(F244="",G244=""),"",G244-F244)
A245: 46059 | B245: 星期五 | C245: 餐饮 | D245: 早餐 | H245: =IF(AND(F245="",G245=""),"",G245-F245)
A246: 46059 | B246: 星期五 | C246: 餐饮 | D246: 中餐 | H246: =IF(AND(F246="",G246=""),"",G246-F246)
A247: 46059 | B247: 星期五 | C247: 餐饮 | D247: 晚餐 | H247: =IF(AND(F247="",G247=""),"",G247-F247)
A248: 46059 | B248: 星期五 | C248: 奶茶/咖啡 | D248: 奶茶/咖啡 | H248: =IF(AND(F248="",G248=""),"",G248-F248)
A249: 46059 | B249: 星期五 | C249: 其他 | D249: 其他 | H249: =IF(AND(F249="",G249=""),"",G249-F249)
A250: 46059 | B250: 星期五 | C250: 其他 | D250: 其他 | H250: =IF(AND(F250="",G250=""),"",G250-F250)
... A280: 46064 | B280: 星期三 | C280: 其他 | D280: 其他 | H280: =IF(AND(F280="",G280=""),"",G280-F280)
A281: 本周小计 | F281: =SUMIFS($F:$F,$A:$A,">="&DATE(2026,2,5),$A:$A,"<="&DATE(2026,2,11)) | G281: =SUMIFS($G:$G,$A:$A,">="&DATE(2026,2,5),$A:$A,"<="&DATE(2026,2,11)) | H281: =G281-F281
A284: 2026年2月｜第二周（2月12日 - 2月18日）
A285: 日期 | B285: 星期 | C285: 分类 | D285: 事项 | E285: 详情 | F285: 支出金额 | G285: 收入金额 | H285: 当笔净额 | I285: 支付方式 | J285: 备注
A286: 46065 | B286: 星期四 | C286: 餐饮 | D286: 早餐 | H286: =IF(AND(F286="",G286=""),"",G286-F286)
...

Sheet 按周汇总
A1: 按周汇总
A2: 周次 | B2: 起始日期 | C2: 结束日期 | D2: 支出合计 | E2: 收入合计 | F2: 本周净额 | G2: 累计余额 | H2: 备注
A3: 第1周 | B3: 46023 | C3: 46029 | D3: =SUMIFS('流水记账'!$F:$F,'流水记账'!$A:$A,">="&DATE(2026,1,1),'流水记账'!$A:$A,"<="&DATE(2026,1,7)) | E3: =SUMIFS('流水记账'!$G:$G,'流水记账'!$A:$A,">="&DATE(2026,1,1),'流水记账'!$A:$A,"<="&DATE(2026,1,7)) | F3: =E3-D3 | G3: ='按月汇总'!$B$2+SUM($F$3:F3)
A4: 第2周 | B4: 46030 | C4: 46036 | D4: =SUMIFS('流水记账'!$F:$F,'流水记账'!$A:$A,">="&DATE(2026,1,8),'流水记账'!$A:$A,"<="&DATE(2026,1,14)) | E4: =SUMIFS('流水记账'!$G:$G,'流水记账'!$A:$A,">="&DATE(2026,1,8),'流水记账'!$A:$A,"<="&DATE(2026,1,14)) | F4: =E4-D4 | G4: ='按月汇总'!$B$2+SUM($F$3:F4)
A5: 第3周 | B5: 46037 | C5: 46043 | D5: =SUMIFS('流水记账'!$F:$F,'流水记账'!$A:$A,">="&DATE(2026,1,15),'流水记账'!$A:$A,"<="&DATE(2026,1,21)) | E5: =SUMIFS('流水记账'!$G:$G,'流水记账'!$A:$A,">="&DATE(2026,1,15),'流水记账'!$A:$A,"<="&DATE(2026,1,21)) | F5: =E5-D5 | G5: ='按月汇总'!$B$2+SUM($F$3:F5)
A6: 第4周 | B6: 46044 | C6: 46050 | D6: =SUMIFS('流水记账'!$F:$F,'流水记账'!$A:$A,">="&DATE(2026,1,22),'流水记账'!$A:$A,"<="&DATE(2026,1,28)) | E6: =SUMIFS('流水记账'!$G:$G,'流水记账'!$A:$A,">="&DATE(2026,1,22),'流水记账'!$A:$A,"<="&DATE(2026,1,28)) | F6: =E6-D6 | G6: ='按月汇总'!$B$2+SUM($F$3:F6)
A7: 第5周 | B7: 46051 | C7: 46057 | D7: =SUMIFS('流水记账'!$F:$F,'流水记账'!$A:$A,">="&DATE(2026,1,29),'流水记账'!$A:$A,"<="&DATE(2026,2,4)) | E7: =SUMIFS('流水记账'!$G:$G,'流水记账'!$A:$A,">="&DATE(2026,1,29),'流水记账'!$A:$A,"<="&DATE(2026,2,4)) | F7: =E7-D7 | G7: ='按月汇总'!$B$2+SUM($F$3:F7)
A8: 第6周 | B8: 46058 | C8: 46064 | D8: =SUMIFS('流水记账'!$F:$F,'流水记账'!$A:$A,">="&DATE(2026,2,5),'流水记账'!$A:$A,"<="&DATE(2026,2,11)) | E8: =SUMIFS('流水记账'!$G:$G,'流水记账'!$A:$A,">="&DATE(2026,2,5),'流水记账'!$A:$A,"<="&DATE(2026,2,11)) | F8: =E8-D8 | G8: ='按月汇总'!$B$2+SUM($F$3:F8)
A9: 第7周 | B9: 46065 | C9: 46071 | D9: =SUMIFS('流水记账'!$F:$F,'流水记账'!$A:$A,">="&DATE(2026,2,12),'流水记账'!$A:$A,"<="&DATE(2026,2,18)) | E9: =SUMIFS('流水记账'!$G:$G,'流水记账'!$A:$A,">="&DATE(2026,2,12),'流水记账'!$A:$A,"<="&DATE(2026,2,18)) | F9: =E9-D9 | G9: ='按月汇总'!$B$2+SUM($F$3:F9)
A10: 第8周 | B10: 46072 | C10: 46078 | D10: =SUMIFS('流水记账'!$F:$F,'流水记账'!$A:$A,">="&DATE(2026,2,19),'流水记账'!$A:$A,"<="&DATE(2026,2,25)) | E10: =SUMIFS('流水记账'!$G:$G,'流水记账'!$A:$A,">="&DATE(2026,2,19),'流水记账'!$A:$A,"<="&DATE(2026,2,25)) | F10: =E10-D10 | G10: ='按月汇总'!$B$2+SUM($F$3:F10)
A11: 第9周 | B11: 46079 | C11: 46085 | D11: =SUMIFS('流水记账'!$F:$F,'流水记账'!$A:$A,">="&DATE(2026,2,26),'流水记账'!$A:$A,"<="&DATE(2026,3,4)) | E11: =SUMIFS('流水记账'!$G:$G,'流水记账'!$A:$A,">="&DATE(2026,2,26),'流水记账'!$A:$A,"<="&DATE(2026,3,4)) | F11: =E11-D11 | G11: ='按月汇总'!$B$2+SUM($F$3:F11)
A12: 第10周 | B12: 46086 | C12: 46092 | D12: =SUMIFS('流水记账'!$F:$F,'流水记账'!$A:$A,">="&DATE(2026,3,5),'流水记账'!$A:$A,"<="&DATE(2026,3,11)) | E12: =SUMIFS('流水记账'!$G:$G,'流水记账'!$A:$A,">="&DATE(2026,3,5),'流水记账'!$A:$A,"<="&DATE(2026,3,11)) | F12: =E12-D12 | G12: ='按月汇总'!$B$2+SUM($F$3:F12)
A13: 第11周 | B13: 46093 | C13: 46099 | D13: =SUMIFS('流水记账'!$F:$F,'流水记账'!$A:$A,">="&DATE(2026,3,12),'流水记账'!$A:$A,"<="&DATE(2026,3,18)) | E13: =SUMIFS('流水记账'!$G:$G,'流水记账'!$A:$A,">="&DATE(2026,3,12),'流水记账'!$A:$A,"<="&DATE(2026,3,18)) | F13: =E13-D13 | G13: ='按月汇总'!$B$2+SUM($F$3:F13)
A14: 第12周 | B14: 46100 | C14: 46106 | D14: =SUMIFS('流水记账'!$F:$F,'流水记账'!$A:$A,">="&DATE(2026,3,19),'流水记账'!$A:$A,"<="&DATE(2026,3,25)) | E14: =SUMIFS('流水记账'!$G:$G,'流水记账'!$A:$A,">="&DATE(2026,3,19),'流水记账'!$A:$A,"<="&DATE(2026,3,25)) | F14: =E14-D14 | G14: ='按月汇总'!$B$2+SUM($F$3:F14)
A15: 第13周 | B15: 46107 | C15: 46113 | D15: =SUMIFS('流水记账'!$F:$F,'流水记账'!$A:$A,">="&DATE(2026,3,26),'流水记账'!$A:$A,"<="&DATE(2026,4,1)) | E15: =SUMIFS('流水记账'!$G:$G,'流水记账'!$A:$A,">="&DATE(2026,3,26),'流水记账'!$A:$A,"<="&DATE(2026,4,1)) | F15: =E15-D15 | G15: ='按月汇总'!$B$2+SUM($F$3:F15)
A16: 第14周 | B16: 46114 | C16: 46120 | D16: =SUMIFS('流水记账'!$F:$F,'流水记账'!$A:$A,">="&DATE(2026,4,2),'流水记账'!$A:$A,"<="&DATE(2026,4,8)) | E16: =SUMIFS('流水记账'!$G:$G,'流水记账'!$A:$A,">="&DATE(2026,4,2),'流水记账'!$A:$A,"<="&DATE(2026,4,8)) | F16: =E16-D16 | G16: ='按月汇总'!$B$2+SUM($F$3:F16)
A17: 第15周 | B17: 46121 | C17: 46127 | D17: =SUMIFS('流水记账'!$F:$F,'流水记账'!$A:$A,">="&DATE(2026,4,9),'流水记账'!$A:$A,"<="&DATE(2026,4,15)) | E17: =SUMIFS('流水记账'!$G:$G,'流水记账'!$A:$A,">="&DATE(2026,4,9),'流水记账'!$A:$A,"<="&DATE(2026,4,15)) | F17: =E17-D17 | G17: ='按月汇总'!$B$2+SUM($F$3:F17)
A18: 第16周 | B18: 46128 | C18: 46134 | D18: =SUMIFS('流水记账'!$F:$F,'流水记账'!$A:$A,">="&DATE(2026,4,16),'流水记账'!$A:$A,"<="&DATE(2026,4,22)) | E18: =SUMIFS('流水记账'!$G:$G,'流水记账'!$A:$A,">="&DATE(2026,4,16),'流水记账'!$A:$A,"<="&DATE(2026,4,22)) | F18: =E18-D18 | G18: ='按月汇总'!$B$2+SUM($F$3:F18)
A19: 第17周 | B19: 46135 | C19: 46141 | D19: =SUMIFS('流水记账'!$F:$F,'流水记账'!$A:$A,">="&DATE(2026,4,23),'流水记账'!$A:$A,"<="&DATE(2026,4,29)) | E19: =SUMIFS('流水记账'!$G:$G,'流水记账'!$A:$A,">="&DATE(2026,4,23),'流水记账'!$A:$A,"<="&DATE(2026,4,29)) | F19: =E19-D19 | G19: ='按月汇总'!$B$2+SUM($F$3:F19)
A20: 第18周 | B20: 46142 | C20: 46148 | D20: =SUMIFS('流水记账'!$F:$F,'流水记账'!$A:$A,">="&DATE(2026,4,30),'流水记账'!$A:$A,"<="&DATE(2026,5,6)) | E20: =SUMIFS('流水记账'!$G:$G,'流水记账'!$A:$A,">="&DATE(2026,4,30),'流水记账'!$A:$A,"<="&DATE(2026,5,6)) | F20: =E20-D20 | G20: ='按月汇总'!$B$2+SUM($F$3:F20)
A21: 第19周 | B21: 46149 | C21: 46155 | D21: =SUMIFS('流水记账'!$F:$F,'流水记账'!$A:$A,">="&DATE(2026,5,7),'流水记账'!$A:$A,"<="&DATE(2026,5,13)) | E21: =SUMIFS('流水记账'!$G:$G,'流水记账'!$A:$A,">="&DATE(2026,5,7),'流水记账'!$A:$A,"<="&DATE(2026,5,13)) | F21: =E21-D21 | G21: ='按月汇总'!$B$2+SUM($F$3:F21)
A22: 第20周 | B22: 46156 | C22: 46162 | D22: =SUMIFS('流水记账'!$F:$F,'流水记账'!$A:$A,">="&DATE(2026,5,14),'流水记账'!$A:$A,"<="&DATE(2026,5,20)) | E22: =SUMIFS('流水记账'!$G:$G,'流水记账'!$A:$A,">="&DATE(2026,5,14),'流水记账'!$A:$A,"<="&DATE(2026,5,20)) | F22: =E22-D22 | G22: ='按月汇总'!$B$2+SUM($F$3:F22)
A23: 第21周 | B23: 46163 | C23: 46169 | D23: =SUMIFS('流水记账'!$F:$F,'流水记账'!$A:$A,">="&DATE(2026,5,21),'流水记账'!$A:$A,"<="&DATE(2026,5,27)) | E23: =SUMIFS('流水记账'!$G:$G,'流水记账'!$A:$A,">="&DATE(2026,5,21),'流水记账'!$A:$A,"<="&DATE(2026,5,27)) | F23: =E23-D23 | G23: ='按月汇总'!$B$2+SUM($F$3:F23)
A24: 第22周 | B24: 46170 | C24: 46176 | D24: =SUMIFS('流水记账'!$F:$F,'流水记账'!$A:$A,">="&DATE(2026,5,28),'流水记账'!$A:$A,"<="&DATE(2026,6,3)) | E24: =SUMIFS('流水记账'!$G:$G,'流水记账'!$A:$A,">="&DATE(2026,5,28),'流水记账'!$A:$A,"<="&DATE(2026,6,3)) | F24: =E24-D24 | G24: ='按月汇总'!$B$2+SUM($F$3:F24)
A25: 第23周 | B25: 46177 | C25: 46183 | D25: =SUMIFS('流水记账'!$F:$F,'流水记账'!$A:$A,">="&DATE(2026,6,4),'流水记账'!$A:$A,"<="&DATE(2026,6,10)) | E25: =SUMIFS('流水记账'!$G:$G,'流水记账'!$A:$A,">="&DATE(2026,6,4),'流水记账'!$A:$A,"<="&DATE(2026,6,10)) | F25: =E25-D25 | G25: ='按月汇总'!$B$2+SUM($F$3:F25)
A26: 第24周 | B26: 46184 | C26: 46190 | D26: =SUMIFS('流水记账'!$F:$F,'流水记账'!$A:$A,">="&DATE(2026,6,11),'流水记账'!$A:$A,"<="&DATE(2026,6,17)) | E26: =SUMIFS('流水记账'!$G:$G,'流水记账'!$A:$A,">="&DATE(2026,6,11),'流水记账'!$A:$A,"<="&DATE(2026,6,17)) | F26: =E26-D26 | G26: ='按月汇总'!$B$2+SUM($F$3:F26)
A27: 第25周 | B27: 46191 | C27: 46197 | D27: =SUMIFS('流水记账'!$F:$F,'流水记账'!$A:$A,">="&DATE(2026,6,18),'流水记账'!$A:$A,"<="&DATE(2026,6,24)) | E27: =SUMIFS('流水记账'!$G:$G,'流水记账'!$A:$A,">="&DATE(2026,6,18),'流水记账'!$A:$A,"<="&DATE(2026,6,24)) | F27: =E27-D27 | G27: ='按月汇总'!$B$2+SUM($F$3:F27)
A28: 第26周 | B28: 46198 | C28: 46204 | D28: =SUMIFS('流水记账'!$F:$F,'流水记账'!$A:$A,">="&DATE(2026,6,25),'流水记账'!$A:$A,"<="&DATE(2026,7,1)) | E28: =SUMIFS('流水记账'!$G:$G,'流水记账'!$A:$A,">="&DATE(2026,6,25),'流水记账'!$A:$A,"<="&DATE(2026,7,1)) | F28: =E28-D28 | G28: ='按月汇总'!$B$2+SUM($F$3:F28)
A29: 第27周 | B29: 46205 | C29: 46211 | D29: =SUMIFS('流水记账'!$F:$F,'流水记账'!$A:$A,">="&DATE(2026,7,2),'流水记账'!$A:$A,"<="&DATE(2026,7,8)) | E29: =SUMIFS('流水记账'!$G:$G,'流水记账'!$A:$A,">="&DATE(2026,7,2),'流水记账'!$A:$A,"<="&DATE(2026,7,8)) | F29: =E29-D29 | G29: ='按月汇总'!$B$2+SUM($F$3:F29)
A30: 第28周 | B30: 46212 | C30: 46218 | D30: =SUMIFS('流水记账'!$F:$F,'流水记账'!$A:$A,">="&DATE(2026,7,9),'流水记账'!$A:$A,"<="&DATE(2026,7,15)) | E30: =SUMIFS('流水记账'!$G:$G,'流水记账'!$A:$A,">="&DATE(2026,7,9),'流水记账'!$A:$A,"<="&DATE(2026,7,15)) | F30: =E30-D30 | G30: ='按月汇总'!$B$2+SUM($F$3:F30)
A31: 第29周 | B31: 46219 | C31: 46225 | D31: =SUMIFS('流水记账'!$F:$F,'流水记账'!$A:$A,">="&DATE(2026,7,16),'流水记账'!$A:$A,"<="&DATE(2026,7,22)) | E31: =SUMIFS('流水记账'!$G:$G,'流水记账'!$A:$A,">="&DATE(2026,7,16),'流水记账'!$A:$A,"<="&DATE(2026,7,22)) | F31: =E31-D31 | G31: ='按月汇总'!$B$2+SUM($F$3:F31)
A32: 第30周 | B32: 46226 | C32: 46232 | D32: =SUMIFS('流水记账'!$F:$F,'流水记账'!$A:$A,">="&DATE(2026,7,23),'流水记账'!$A:$A,"<="&DATE(2026,7,29)) | E32: =SUMIFS('流水记账'!$G:$G,'流水记账'!$A:$A,">="&DATE(2026,7,23),'流水记账'!$A:$A,"<="&DATE(2026,7,29)) | F32: =E32-D32 | G32: ='按月汇总'!$B$2+SUM($F$3:F32)
A33: 第31周 | B33: 46233 | C33: 46239 | D33: =SUMIFS('流水记账'!$F:$F,'流水记账'!$A:$A,">="&DATE(2026,7,30),'流水记账'!$A:$A,"<="&DATE(2026,8,5)) | E33: =SUMIFS('流水记账'!$G:$G,'流水记账'!$A:$A,">="&DATE(2026,7,30),'流水记账'!$A:$A,"<="&DATE(2026,8,5)) | F33: =E33-D33 | G33: ='按月汇总'!$B$2+SUM($F$3:F33)
A34: 第32周 | B34: 46240 | C34: 46246 | D34: =SUMIFS('流水记账'!$F:$F,'流水记账'!$A:$A,">="&DATE(2026,8,6),'流水记账'!$A:$A,"<="&DATE(2026,8,12)) | E34: =SUMIFS('流水记账'!$G:$G,'流水记账'!$A:$A,">="&DATE(2026,8,6),'流水记账'!$A:$A,"<="&DATE(2026,8,12)) | F34: =E34-D34 | G34: ='按月汇总'!$B$2+SUM($F$3:F34)
A35: 第33周 | B35: 46247 | C35: 46253 | D35: =SUMIFS('流水记账'!$F:$F,'流水记账'!$A:$A,">="&DATE(2026,8,13),'流水记账'!$A:$A,"<="&DATE(2026,8,19)) | E35: =SUMIFS('流水记账'!$G:$G,'流水记账'!$A:$A,">="&DATE(2026,8,13),'流水记账'!$A:$A,"<="&DATE(2026,8,19)) | F35: =E35-D35 | G35: ='按月汇总'!$B$2+SUM($F$3:F35)
A36: 第34周 | B36: 46254 | C36: 46260 | D36: =SUMIFS('流水记账'!$F:$F,'流水记账'!$A:$A,">="&DATE(2026,8,20),'流水记账'!$A:$A,"<="&DATE(2026,8,26)) | E36: =SUMIFS('流水记账'!$G:$G,'流水记账'!$A:$A,">="&DATE(2026,8,20),'流水记账'!$A:$A,"<="&DATE(2026,8,26)) | F36: =E36-D36 | G36: ='按月汇总'!$B$2+SUM($F$3:F36)
A37: 第35周 | B37: 46261 | C37: 46267 | D37: =SUMIFS('流水记账'!$F:$F,'流水记账'!$A:$A,">="&DATE(2026,8,27),'流水记账'!$A:$A,"<="&DATE(2026,9,2)) | E37: =SUMIFS('流水记账'!$G:$G,'流水记账'!$A:$A,">="&DATE(2026,8,27),'流水记账'!$A:$A,"<="&DATE(2026,9,2)) | F37: =E37-D37 | G37: ='按月汇总'!$B$2+SUM($F$3:F37)
A38: 第36周 | B38: 46268 | C38: 46274 | D38: =SUMIFS('流水记账'!$F:$F,'流水记账'!$A:$A,">="&DATE(2026,9,3),'流水记账'!$A:$A,"<="&DATE(2026,9,9)) | E38: =SUMIFS('流水记账'!$G:$G,'流水记账'!$A:$A,">="&DATE(2026,9,3),'流水记账'!$A:$A,"<="&DATE(2026,9,9)) | F38: =E38-D38 | G38: ='按月汇总'!$B$2+SUM($F$3:F38)
A39: 第37周 | B39: 46275 | C39: 46281 | D39: =SUMIFS('流水记账'!$F:$F,'流水记账'!$A:$A,">="&DATE(2026,9,10),'流水记账'!$A:$A,"<="&DATE(2026,9,16)) | E39: =SUMIFS('流水记账'!$G:$G,'流水记账'!$A:$A,">="&DATE(2026,9,10),'流水记账'!$A:$A,"<="&DATE(2026,9,16)) | F39: =E39-D39 | G39: ='按月汇总'!$B$2+SUM($F$3:F39)
A40: 第38周 | B40: 46282 | C40: 46288 | D40: =SUMIFS('流水记账'!$F:$F,'流水记账'!$A:$A,">="&DATE(2026,9,17),'流水记账'!$A:$A,"<="&DATE(2026,9,23)) | E40: =SUMIFS('流水记账'!$G:$G,'流水记账'!$A:$A,">="&DATE(2026,9,17),'流水记账'!$A:$A,"<="&DATE(2026,9,23)) | F40: =E40-D40 | G40: ='按月汇总'!$B$2+SUM($F$3:F40)
A41: 第39周 | B41: 46289 | C41: 46295 | D41: =SUMIFS('流水记账'!$F:$F,'流水记账'!$A:$A,">="&DATE(2026,9,24),'流水记账'!$A:$A,"<="&DATE(2026,9,30)) | E41: =SUMIFS('流水记账'!$G:$G,'流水记账'!$A:$A,">="&DATE(2026,9,24),'流水记账'!$A:$A,"<="&DATE(2026,9,30)) | F41: =E41-D41 | G41: ='按月汇总'!$B$2+SUM($F$3:F41)
A42: 第40周 | B42: 46296 | C42: 46302 | D42: =SUMIFS('流水记账'!$F:$F,'流水记账'!$A:$A,">="&DATE(2026,10,1),'流水记账'!$A:$A,"<="&DATE(2026,10,7)) | E42: =SUMIFS('流水记账'!$G:$G,'流水记账'!$A:$A,">="&DATE(2026,10,1),'流水记账'!$A:$A,"<="&DATE(2026,10,7)) | F42: =E42-D42 | G42: ='按月汇总'!$B$2+SUM($F$3:F42)
A43: 第41周 | B43: 46303 | C43: 46309 | D43: =SUMIFS('流水记账'!$F:$F,'流水记账'!$A:$A,">="&DATE(2026,10,8),'流水记账'!$A:$A,"<="&DATE(2026,10,14)) | E43: =SUMIFS('流水记账'!$G:$G,'流水记账'!$A:$A,">="&DATE(2026,10,8),'流水记账'!$A:$A,"<="&DATE(2026,10,14)) | F43: =E43-D43 | G43: ='按月汇总'!$B$2+SUM($F$3:F43)
A44: 第42周 | B44: 46310 | C44: 46316 | D44: =SUMIFS('流水记账'!$F:$F,'流水记账'!$A:$A,">="&DATE(2026,10,15),'流水记账'!$A:$A,"<="&DATE(2026,10,21)) | E44: =SUMIFS('流水记账'!$G:$G,'流水记账'!$A:$A,">="&DATE(2026,10,15),'流水记账'!$A:$A,"<="&DATE(2026,10,21)) | F44: =E44-D44 | G44: ='按月汇总'!$B$2+SUM($F$3:F44)
A45: 第43周 | B45: 46317 | C45: 46323 | D45: =SUMIFS('流水记账'!$F:$F,'流水记账'!$A:$A,">="&DATE(2026,10,22),'流水记账'!$A:$A,"<="&DATE(2026,10,28)) | E45: =SUMIFS('流水记账'!$G:$G,'流水记账'!$A:$A,">="&DATE(2026,10,22),'流水记账'!$A:$A,"<="&DATE(2026,10,28)) | F45: =E45-D45 | G45: ='按月汇总'!$B$2+SUM($F$3:F45)
A46: 第44周 | B46: 46324 | C46: 46330 | D46: =SUMIFS('流水记账'!$F:$F,'流水记账'!$A:$A,">="&DATE(2026,10,29),'流水记账'!$A:$A,"<="&DATE(2026,11,4)) | E46: =SUMIFS('流水记账'!$G:$G,'流水记账'!$A:$A,">="&DATE(2026,10,29),'流水记账'!$A:$A,"<="&DATE(2026,11,4)) | F46: =E46-D46 | G46: ='按月汇总'!$B$2+SUM($F$3:F46)
A47: 第45周 | B47: 46331 | C47: 46337 | D47: =SUMIFS('流水记账'!$F:$F,'流水记账'!$A:$A,">="&DATE(2026,11,5),'流水记账'!$A:$A,"<="&DATE(2026,11,11)) | E47: =SUMIFS('流水记账'!$G:$G,'流水记账'!$A:$A,">="&DATE(2026,11,5),'流水记账'!$A:$A,"<="&DATE(2026,11,11)) | F47: =E47-D47 | G47: ='按月汇总'!$B$2+SUM($F$3:F47)
A48: 第46周 | B48: 46338 | C48: 46344 | D48: =SUMIFS('流水记账'!$F:$F,'流水记账'!$A:$A,">="&DATE(2026,11,12),'流水记账'!$A:$A,"<="&DATE(2026,11,18)) | E48: =SUMIFS('流水记账'!$G:$G,'流水记账'!$A:$A,">="&DATE(2026,11,12),'流水记账'!$A:$A,"<="&DATE(2026,11,18)) | F48: =E48-D48 | G48: ='按月汇总'!$B$2+SUM($F$3:F48)
A49: 第47周 | B49: 46345 | C49: 46351 | D49: =SUMIFS('流水记账'!$F:$F,'流水记账'!$A:$A,">="&DATE(2026,11,19),'流水记账'!$A:$A,"<="&DATE(2026,11,25)) | E49: =SUMIFS('流水记账'!$G:$G,'流水记账'!$A:$A,">="&DATE(2026,11,19),'流水记账'!$A:$A,"<="&DATE(2026,11,25)) | F49: =E49-D49 | G49: ='按月汇总'!$B$2+SUM($F$3:F49)
A50: 第48周 | B50: 46352 | C50: 46358 | D50: =SUMIFS('流水记账'!$F:$F,'流水记账'!$A:$A,">="&DATE(2026,11,26),'流水记账'!$A:$A,"<="&DATE(2026,12,2)) | E50: =SUMIFS('流水记账'!$G:$G,'流水记账'!$A:$A,">="&DATE(2026,11,26),'流水记账'!$A:$A,"<="&DATE(2026,12,2)) | F50: =E50-D50 | G50: ='按月汇总'!$B$2+SUM($F$3:F50)
A51: 第49周 | B51: 46359 | C51: 46365 | D51: =SUMIFS('流水记账'!$F:$F,'流水记账'!$A:$A,">="&DATE(2026,12,3),'流水记账'!$A:$A,"<="&DATE(2026,12,9)) | E51: =SUMIFS('流水记账'!$G:$G,'流水记账'!$A:$A,">="&DATE(2026,12,3),'流水记账'!$A:$A,"<="&DATE(2026,12,9)) | F51: =E51-D51 | G51: ='按月汇总'!$B$2+SUM($F$3:F51)
A52: 第50周 | B52: 46366 | C52: 46372 | D52: =SUMIFS('流水记账'!$F:$F,'流水记账'!$A:$A,">="&DATE(2026,12,10),'流水记账'!$A:$A,"<="&DATE(2026,12,16)) | E52: =SUMIFS('流水记账'!$G:$G,'流水记账'!$A:$A,">="&DATE(2026,12,10),'流水记账'!$A:$A,"<="&DATE(2026,12,16)) | F52: =E52-D52 | G52: ='按月汇总'!$B$2+SUM($F$3:F52)
A53: 第51周 | B53: 46373 | C53: 46379 | D53: =SUMIFS('流水记账'!$F:$F,'流水记账'!$A:$A,">="&DATE(2026,12,17),'流水记账'!$A:$A,"<="&DATE(2026,12,23)) | E53: =SUMIFS('流水记账'!$G:$G,'流水记账'!$A:$A,">="&DATE(2026,12,17),'流水记账'!$A:$A,"<="&DATE(2026,12,23)) | F53: =E53-D53 | G53: ='按月汇总'!$B$2+SUM($F$3:F53)
A54: 第52周 | B54: 46380 | C54: 46386 | D54: =SUMIFS('流水记账'!$F:$F,'流水记账'!$A:$A,">="&DATE(2026,12,24),'流水记账'!$A:$A,"<="&DATE(2026,12,30)) | E54: =SUMIFS('流水记账'!$G:$G,'流水记账'!$A:$A,">="&DATE(2026,12,24),'流水记账'!$A:$A,"<="&DATE(2026,12,30)) | F54: =E54-D54 | G54: ='按月汇总'!$B$2+SUM($F$3:F54)
A55: 第53周 | B55: 46387 | C55: 46393 | D55: =SUMIFS('流水记账'!$F:$F,'流水记账'!$A:$A,">="&DATE(2026,12,31),'流水记账'!$A:$A,"<="&DATE(2027,1,6)) | E55: =SUMIFS('流水记账'!$G:$G,'流水记账'!$A:$A,">="&DATE(2026,12,31),'流水记账'!$A:$A,"<="&DATE(2027,1,6)) | F55: =E55-D55 | G55: ='按月汇总'!$B$2+SUM($F$3:F55)
A56: 第54周 | B56: 46394 | C56: 46400 | D56: =SUMIFS('流水记账'!$F:$F,'流水记账'!$A:$A,">="&DATE(2027,1,7),'流水记账'!$A:$A,"<="&DATE(2027,1,13)) | E56: =SUMIFS('流水记账'!$G:$G,'流水记账'!$A:$A,">="&DATE(2027,1,7),'流水记账'!$A:$A,"<="&DATE(2027,1,13)) | F56: =E56-D56 | G56: ='按月汇总'!$B$2+SUM($F$3:F56)
A57: 第55周 | B57: 46401 | C57: 46407 | D57: =SUMIFS('流水记账'!$F:$F,'流水记账'!$A:$A,">="&DATE(2027,1,14),'流水记账'!$A:$A,"<="&DATE(2027,1,20)) | E57: =SUMIFS('流水记账'!$G:$G,'流水记账'!$A:$A,">="&DATE(2027,1,14),'流水记账'!$A:$A,"<="&DATE(2027,1,20)) | F57: =E57-D57 | G57: ='按月汇总'!$B$2+SUM($F$3:F57)
A58: 第56周 | B58: 46408 | C58: 46414 | D58: =SUMIFS('流水记账'!$F:$F,'流水记账'!$A:$A,">="&DATE(2027,1,21),'流水记账'!$A:$A,"<="&DATE(2027,1,27)) | E58: =SUMIFS('流水记账'!$G:$G,'流水记账'!$A:$A,">="&DATE(2027,1,21),'流水记账'!$A:$A,"<="&DATE(2027,1,27)) | F58: =E58-D58 | G58: ='按月汇总'!$B$2+SUM($F$3:F58)
A59: 第57周 | B59: 46415 | C59: 46421 | D59: =SUMIFS('流水记账'!$F:$F,'流水记账'!$A:$A,">="&DATE(2027,1,28),'流水记账'!$A:$A,"<="&DATE(2027,2,3)) | E59: =SUMIFS('流水记账'!$G:$G,'流水记账'!$A:$A,">="&DATE(2027,1,28),'流水记账'!$A:$A,"<="&DATE(2027,2,3)) | F59: =E59-D59 | G59: ='按月汇总'!$B$2+SUM($F$3:F59)
A60: 第58周 | B60: 46422 | C60: 46428 | D60: =SUMIFS('流水记账'!$F:$F,'流水记账'!$A:$A,">="&DATE(2027,2,4),'流水记账'!$A:$A,"<="&DATE(2027,2,10)) | E60: =SUMIFS('流水记账'!$G:$G,'流水记账'!$A:$A,">="&DATE(2027,2,4),'流水记账'!$A:$A,"<="&DATE(2027,2,10)) | F60: =E60-D60 | G60: ='按月汇总'!$B$2+SUM($F$3:F60)
A61: 第59周 | B61: 46429 | C61: 46435 | D61: =SUMIFS('流水记账'!$F:$F,'流水记账'!$A:$A,">="&DATE(2027,2,11),'流水记账'!$A:$A,"<="&DATE(2027,2,17)) | E61: =SUMIFS('流水记账'!$G:$G,'流水记账'!$A:$A,">="&DATE(2027,2,11),'流水记账'!$A:$A,"<="&DATE(2027,2,17)) | F61: =E61-D61 | G61: ='按月汇总'!$B$2+SUM($F$3:F61)
A62: 第60周 | B62: 46436 | C62: 46442 | D62: =SUMIFS('流水记账'!$F:$F,'流水记账'!$A:$A,">="&DATE(2027,2,18),'流水记账'!$A:$A,"<="&DATE(2027,2,24)) | E62: =SUMIFS('流水记账'!$G:$G,'流水记账'!$A:$A,">="&DATE(2027,2,18),'流水记账'!$A:$A,"<="&DATE(2027,2,24)) | F62: =E62-D62 | G62: ='按月汇总'!$B$2+SUM($F$3:F62)
A63: 第61周 | B63: 46443 | C63: 46449 | D63: =SUMIFS('流水记账'!$F:$F,'流水记账'!$A:$A,">="&DATE(2027,2,25),'流水记账'!$A:$A,"<="&DATE(2027,3,3)) | E63: =SUMIFS('流水记账'!$G:$G,'流水记账'!$A:$A,">="&DATE(2027,2,25),'流水记账'!$A:$A,"<="&DATE(2027,3,3)) | F63: =E63-D63 | G63: ='按月汇总'!$B$2+SUM($F$3:F63)
A64: 第62周 | B64: 46450 | C64: 46456 | D64: =SUMIFS('流水记账'!$F:$F,'流水记账'!$A:$A,">="&DATE(2027,3,4),'流水记账'!$A:$A,"<="&DATE(2027,3,10)) | E64: =SUMIFS('流水记账'!$G:$G,'流水记账'!$A:$A,">="&DATE(2027,3,4),'流水记账'!$A:$A,"<="&DATE(2027,3,10)) | F64: =E64-D64 | G64: ='按月汇总'!$B$2+SUM($F$3:F64)
A65: 第63周 | B65: 46457 | C65: 46463 | D65: =SUMIFS('流水记账'!$F:$F,'流水记账'!$A:$A,">="&DATE(2027,3,11),'流水记账'!$A:$A,"<="&DATE(2027,3,17)) | E65: =SUMIFS('流水记账'!$G:$G,'流水记账'!$A:$A,">="&DATE(2027,3,11),'流水记账'!$A:$A,"<="&DATE(2027,3,17)) | F65: =E65-D65 | G65: ='按月汇总'!$B$2+SUM($F$3:F65)
A66: 第64周 | B66: 46464 | C66: 46470 | D66: =SUMIFS('流水记账'!$F:$F,'流水记账'!$A:$A,">="&DATE(2027,3,18),'流水记账'!$A:$A,"<="&DATE(2027,3,24)) | E66: =SUMIFS('流水记账'!$G:$G,'流水记账'!$A:$A,">="&DATE(2027,3,18),'流水记账'!$A:$A,"<="&DATE(2027,3,24)) | F66: =E66-D66 | G66: ='按月汇总'!$B$2+SUM($F$3:F66)
A67: 第65周 | B67: 46471 | C67: 46477 | D67: =SUMIFS('流水记账'!$F:$F,'流水记账'!$A:$A,">="&DATE(2027,3,25),'流水记账'!$A:$A,"<="&DATE(2027,3,31)) | E67: =SUMIFS('流水记账'!$G:$G,'流水记账'!$A:$A,">="&DATE(2027,3,25),'流水记账'!$A:$A,"<="&DATE(2027,3,31)) | F67: =E67-D67 | G67: ='按月汇总'!$B$2+SUM($F$3:F67)
A68: 第66周 | B68: 46478 | C68: 46484 | D68: =SUMIFS('流水记账'!$F:$F,'流水记账'!$A:$A,">="&DATE(2027,4,1),'流水记账'!$A:$A,"<="&DATE(2027,4,7)) | E68: =SUMIFS('流水记账'!$G:$G,'流水记账'!$A:$A,">="&DATE(2027,4,1),'流水记账'!$A:$A,"<="&DATE(2027,4,7)) | F68: =E68-D68 | G68: ='按月汇总'!$B$2+SUM($F$3:F68)
A69: 第67周 | B69: 46485 | C69: 46491 | D69: =SUMIFS('流水记账'!$F:$F,'流水记账'!$A:$A,">="&DATE(2027,4,8),'流水记账'!$A:$A,"<="&DATE(2027,4,14)) | E69: =SUMIFS('流水记账'!$G:$G,'流水记账'!$A:$A,">="&DATE(2027,4,8),'流水记账'!$A:$A,"<="&DATE(2027,4,14)) | F69: =E69-D69 | G69: ='按月汇总'!$B$2+SUM($F$3:F69)
A70: 第68周 | B70: 46492 | C70: 46498 | D70: =SUMIFS('流水记账'!$F:$F,'流水记账'!$A:$A,">="&DATE(2027,4,15),'流水记账'!$A:$A,"<="&DATE(2027,4,21)) | E70: =SUMIFS('流水记账'!$G:$G,'流水记账'!$A:$A,">="&DATE(2027,4,15),'流水记账'!$A:$A,"<="&DATE(2027,4,21)) | F70: =E70-D70 | G70: ='按月汇总'!$B$2+SUM($F$3:F70)
A71: 第69周 | B71: 46499 | C71: 46505 | D71: =SUMIFS('流水记账'!$F:$F,'流水记账'!$A:$A,">="&DATE(2027,4,22),'流水记账'!$A:$A,"<="&DATE(2027,4,28)) | E71: =SUMIFS('流水记账'!$G:$G,'流水记账'!$A:$A,">="&DATE(2027,4,22),'流水记账'!$A:$A,"<="&DATE(2027,4,28)) | F71: =E71-D71 | G71: ='按月汇总'!$B$2+SUM($F$3:F71)
A72: 第70周 | B72: 46506 | C72: 46512 | D72: =SUMIFS('流水记账'!$F:$F,'流水记账'!$A:$A,">="&DATE(2027,4,29),'流水记账'!$A:$A,"<="&DATE(2027,5,5)) | E72: =SUMIFS('流水记账'!$G:$G,'流水记账'!$A:$A,">="&DATE(2027,4,29),'流水记账'!$A:$A,"<="&DATE(2027,5,5)) | F72: =E72-D72 | G72: ='按月汇总'!$B$2+SUM($F$3:F72)
A73: 第71周 | B73: 46513 | C73: 46519 | D73: =SUMIFS('流水记账'!$F:$F,'流水记账'!$A:$A,">="&DATE(2027,5,6),'流水记账'!$A:$A,"<="&DATE(2027,5,12)) | E73: =SUMIFS('流水记账'!$G:$G,'流水记账'!$A:$A,">="&DATE(2027,5,6),'流水记账'!$A:$A,"<="&DATE(2027,5,12)) | F73: =E73-D73 | G73: ='按月汇总'!$B$2+SUM($F$3:F73)
A74: 第72周 | B74: 46520 | C74: 46526 | D74: =SUMIFS('流水记账'!$F:$F,'流水记账'!$A:$A,">="&DATE(2027,5,13),'流水记账'!$A:$A,"<="&DATE(2027,5,19)) | E74: =SUMIFS('流水记账'!$G:$G,'流水记账'!$A:$A,">="&DATE(2027,5,13),'流水记账'!$A:$A,"<="&DATE(2027,5,19)) | F74: =E74-D74 | G74: ='按月汇总'!$B$2+SUM($F$3:F74)
A75: 第73周 | B75: 46527 | C75: 46533 | D75: =SUMIFS('流水记账'!$F:$F,'流水记账'!$A:$A,">="&DATE(2027,5,20),'流水记账'!$A:$A,"<="&DATE(2027,5,26)) | E75: =SUMIFS('流水记账'!$G:$G,'流水记账'!$A:$A,">="&DATE(2027,5,20),'流水记账'!$A:$A,"<="&DATE(2027,5,26)) | F75: =E75-D75 | G75: ='按月汇总'!$B$2+SUM($F$3:F75)
A76: 第74周 | B76: 46534 | C76: 46538 | D76: =SUMIFS('流水记账'!$F:$F,'流水记账'!$A:$A,">="&DATE(2027,5,27),'流水记账'!$A:$A,"<="&DATE(2027,5,31)) | E76: =SUMIFS('流水记账'!$G:$G,'流水记账'!$A:$A,">="&DATE(2027,5,27),'流水记账'!$A:$A,"<="&DATE(2027,5,31)) | F76: =E76-D76 | G76: ='按月汇总'!$B$2+SUM($F$3:F76)

Sheet 按月汇总
A1: 按月汇总
A2: 起始余额 | B2: 0 | C2: 总支出 | D2: =SUM(B6:B22) | E2: 总收入 | F2: =SUM(C6:C22)
A3: 总净额 | B3: =SUM(D6:D22) | C3: 当前余额 | D3: =B2+B3
A5: 月份 | B5: 支出合计 | C5: 收入合计 | D5: 本月净额 | E5: 累计余额 | F5: 备注
A6: 2026年1月 | B6: =SUMIFS('流水记账'!$F:$F,'流水记账'!$A:$A,">="&DATE(2026,1,1),'流水记账'!$A:$A,"<"&DATE(2026,2,1)) | C6: =SUMIFS('流水记账'!$G:$G,'流水记账'!$A:$A,">="&DATE(2026,1,1),'流水记账'!$A:$A,"<"&DATE(2026,2,1)) | D6: =C6-B6 | E6: =$B$2+SUM($D$6:D6)
A7: 2026年2月 | B7: =SUMIFS('流水记账'!$F:$F,'流水记账'!$A:$A,">="&DATE(2026,2,1),'流水记账'!$A:$A,"<"&DATE(2026,3,1)) | C7: =SUMIFS('流水记账'!$G:$G,'流水记账'!$A:$A,">="&DATE(2026,2,1),'流水记账'!$A:$A,"<"&DATE(2026,3,1)) | D7: =C7-B7 | E7: =$B$2+SUM($D$6:D7)
A8: 2026年3月 | B8: =SUMIFS('流水记账'!$F:$F,'流水记账'!$A:$A,">="&DATE(2026,3,1),'流水记账'!$A:$A,"<"&DATE(2026,4,1)) | C8: =SUMIFS('流水记账'!$G:$G,'流水记账'!$A:$A,">="&DATE(2026,3,1),'流水记账'!$A:$A,"<"&DATE(2026,4,1)) | D8: =C8-B8 | E8: =$B$2+SUM($D$6:D8)
A9: 2026年4月 | B9: =SUMIFS('流水记账'!$F:$F,'流水记账'!$A:$A,">="&DATE(2026,4,1),'流水记账'!$A:$A,"<"&DATE(2026,5,1)) | C9: =SUMIFS('流水记账'!$G:$G,'流水记账'!$A:$A,">="&DATE(2026,4,1),'流水记账'!$A:$A,"<"&DATE(2026,5,1)) | D9: =C9-B9 | E9: =$B$2+SUM($D$6:D9)
A10: 2026年5月 | B10: =SUMIFS('流水记账'!$F:$F,'流水记账'!$A:$A,">="&DATE(2026,5,1),'流水记账'!$A:$A,"<"&DATE(2026,6,1)) | C10: =SUMIFS('流水记账'!$G:$G,'流水记账'!$A:$A,">="&DATE(2026,5,1),'流水记账'!$A:$A,"<"&DATE(2026,6,1)) | D10: =C10-B10 | E10: =$B$2+SUM($D$6:D10)
A11: 2026年6月 | B11: =SUMIFS('流水记账'!$F:$F,'流水记账'!$A:$A,">="&DATE(2026,6,1),'流水记账'!$A:$A,"<"&DATE(2026,7,1)) | C11: =SUMIFS('流水记账'!$G:$G,'流水记账'!$A:$A,">="&DATE(2026,6,1),'流水记账'!$A:$A,"<"&DATE(2026,7,1)) | D11: =C11-B11 | E11: =$B$2+SUM($D$6:D11)
A12: 2026年7月 | B12: =SUMIFS('流水记账'!$F:$F,'流水记账'!$A:$A,">="&DATE(2026,7,1),'流水记账'!$A:$A,"<"&DATE(2026,8,1)) | C12: =SUMIFS('流水记账'!$G:$G,'流水记账'!$A:$A,">="&DATE(2026,7,1),'流水记账'!$A:$A,"<"&DATE(2026,8,1)) | D12: =C12-B12 | E12: =$B$2+SUM($D$6:D12)
A13: 2026年8月 | B13: =SUMIFS('流水记账'!$F:$F,'流水记账'!$A:$A,">="&DATE(2026,8,1),'流水记账'!$A:$A,"<"&DATE(2026,9,1)) | C13: =SUMIFS('流水记账'!$G:$G,'流水记账'!$A:$A,">="&DATE(2026,8,1),'流水记账'!$A:$A,"<"&DATE(2026,9,1)) | D13: =C13-B13 | E13: =$B$2+SUM($D$6:D13)
A14: 2026年9月 | B14: =SUMIFS('流水记账'!$F:$F,'流水记账'!$A:$A,">="&DATE(2026,9,1),'流水记账'!$A:$A,"<"&DATE(2026,10,1)) | C14: =SUMIFS('流水记账'!$G:$G,'流水记账'!$A:$A,">="&DATE(2026,9,1),'流水记账'!$A:$A,"<"&DATE(2026,10,1)) | D14: =C14-B14 | E14: =$B$2+SUM($D$6:D14)
A15: 2026年10月 | B15: =SUMIFS('流水记账'!$F:$F,'流水记账'!$A:$A,">="&DATE(2026,10,1),'流水记账'!$A:$A,"<"&DATE(2026,11,1)) | C15: =SUMIFS('流水记账'!$G:$G,'流水记账'!$A:$A,">="&DATE(2026,10,1),'流水记账'!$A:$A,"<"&DATE(2026,11,1)) | D15: =C15-B15 | E15: =$B$2+SUM($D$6:D15)
A16: 2026年11月 | B16: =SUMIFS('流水记账'!$F:$F,'流水记账'!$A:$A,">="&DATE(2026,11,1),'流水记账'!$A:$A,"<"&DATE(2026,12,1)) | C16: =SUMIFS('流水记账'!$G:$G,'流水记账'!$A:$A,">="&DATE(2026,11,1),'流水记账'!$A:$A,"<"&DATE(2026,12,1)) | D16: =C16-B16 | E16: =$B$2+SUM($D$6:D16)
A17: 2026年12月 | B17: =SUMIFS('流水记账'!$F:$F,'流水记账'!$A:$A,">="&DATE(2026,12,1),'流水记账'!$A:$A,"<"&DATE(2027,1,1)) | C17: =SUMIFS('流水记账'!$G:$G,'流水记账'!$A:$A,">="&DATE(2026,12,1),'流水记账'!$A:$A,"<"&DATE(2027,1,1)) | D17: =C17-B17 | E17: =$B$2+SUM($D$6:D17)
A18: 2027年1月 | B18: =SUMIFS('流水记账'!$F:$F,'流水记账'!$A:$A,">="&DATE(2027,1,1),'流水记账'!$A:$A,"<"&DATE(2027,2,1)) | C18: =SUMIFS('流水记账'!$G:$G,'流水记账'!$A:$A,">="&DATE(2027,1,1),'流水记账'!$A:$A,"<"&DATE(2027,2,1)) | D18: =C18-B18 | E18: =$B$2+SUM($D$6:D18)
A19: 2027年2月 | B19: =SUMIFS('流水记账'!$F:$F,'流水记账'!$A:$A,">="&DATE(2027,2,1),'流水记账'!$A:$A,"<"&DATE(2027,3,1)) | C19: =SUMIFS('流水记账'!$G:$G,'流水记账'!$A:$A,">="&DATE(2027,2,1),'流水记账'!$A:$A,"<"&DATE(2027,3,1)) | D19: =C19-B19 | E19: =$B$2+SUM($D$6:D19)
A20: 2027年3月 | B20: =SUMIFS('流水记账'!$F:$F,'流水记账'!$A:$A,">="&DATE(2027,3,1),'流水记账'!$A:$A,"<"&DATE(2027,4,1)) | C20: =SUMIFS('流水记账'!$G:$G,'流水记账'!$A:$A,">="&DATE(2027,3,1),'流水记账'!$A:$A,"<"&DATE(2027,4,1)) | D20: =C20-B20 | E20: =$B$2+SUM($D$6:D20)
A21: 2027年4月 | B21: =SUMIFS('流水记账'!$F:$F,'流水记账'!$A:$A,">="&DATE(2027,4,1),'流水记账'!$A:$A,"<"&DATE(2027,5,1)) | C21: =SUMIFS('流水记账'!$G:$G,'流水记账'!$A:$A,">="&DATE(2027,4,1),'流水记账'!$A:$A,"<"&DATE(2027,5,1)) | D21: =C21-B21 | E21: =$B$2+SUM($D$6:D21)
A22: 2027年5月 | B22: =SUMIFS('流水记账'!$F:$F,'流水记账'!$A:$A,">="&DATE(2027,5,1),'流水记账'!$A:$A,"<"&DATE(2027,6,1)) | C22: =SUMIFS('流水记账'!$G:$G,'流水记账'!$A:$A,">="&DATE(2027,5,1),'流水记账'!$A:$A,"<"&DATE(2027,6,1)) | D22: =C22-B22 | E22: =$B$2+SUM($D$6:D22)

Sheet 选项设置
A1: 分类 | B1: 支付方式 | C1: 事项
A2: 餐饮 | B2: 微信 | C2: 奶茶/咖啡
A3: 奶茶/咖啡 | B3: 支付宝 | C3: 交通
A4: 交通 | B4: 银行卡 | C4: 购物
A5: 购物 | B5: 现金 | C5: 娱乐
A6: 娱乐 | B6: 信用卡 | C6: 生活用品
A7: 生活用品 | B7: 其他 | C7: 旅行
A8: 旅行 | C8: 医疗
A9: 医疗 | C9: 人情/礼物
A10: 人情/礼物 | C10: 房租/固定支出
A11: 房租/固定支出 | C11: 其他
A12: 家庭支出 | C12: 早餐
A13: 其他 | C13: 中餐
C14: 晚餐
