Workbook

Sheet 流水记账
A1: 日期 | B1: 星期 | C1: 分类 | D1: 事项 | E1: 支出金额 | F1: 收入金额 | G1: 当笔净额 | H1: 支付方式 | I1: 备注
A2: 2026年6月｜第一周（6月1日 - 6月7日）
A3: 日期 | B3: 星期 | C3: 分类 | D3: 事项 | E3: 支出金额 | F3: 收入金额 | G3: 当笔净额 | H3: 支付方式 | I3: 备注
A4: 46174 | B4: 星期一 | C4: 餐饮 | D4: 早餐 | G4: =IF(AND(E4="",F4=""),"",F4-E4)
A5: 46174 | B5: 星期一 | C5: 餐饮 | D5: 中餐 | G5: =IF(AND(E5="",F5=""),"",F5-E5)
A6: 46174 | B6: 星期一 | C6: 餐饮 | D6: 晚餐 | G6: =IF(AND(E6="",F6=""),"",F6-E6)
A7: 46174 | B7: 星期一 | C7: 奶茶/咖啡 | D7: 奶茶/咖啡 | G7: =IF(AND(E7="",F7=""),"",F7-E7)
A8: 46174 | B8: 星期一 | C8: 其他 | D8: 其他 | G8: =IF(AND(E8="",F8=""),"",F8-E8)
A9: 46174 | B9: 星期一 | C9: 其他 | D9: 其他 | G9: =IF(AND(E9="",F9=""),"",F9-E9)
A10: 46175 | B10: 星期二 | C10: 餐饮 | D10: 早餐 | G10: =IF(AND(E10="",F10=""),"",F10-E10)
A11: 46175 | B11: 星期二 | C11: 餐饮 | D11: 中餐 | G11: =IF(AND(E11="",F11=""),"",F11-E11)
A12: 46175 | B12: 星期二 | C12: 餐饮 | D12: 晚餐 | G12: =IF(AND(E12="",F12=""),"",F12-E12)
A13: 46175 | B13: 星期二 | C13: 奶茶/咖啡 | D13: 奶茶/咖啡 | G13: =IF(AND(E13="",F13=""),"",F13-E13)
A14: 46175 | B14: 星期二 | C14: 其他 | D14: 其他 | G14: =IF(AND(E14="",F14=""),"",F14-E14)
A15: 46175 | B15: 星期二 | C15: 其他 | D15: 其他 | G15: =IF(AND(E15="",F15=""),"",F15-E15)
... A45: 46180 | B45: 星期日 | C45: 其他 | D45: 其他 | G45: =IF(AND(E45="",F45=""),"",F45-E45)
A46: 本周小计 | E46: =SUM(E4:E45) | F46: =SUM(F4:F45) | G46: =SUM(G4:G45)
A49: 2026年6月｜第二周（6月8日 - 6月14日）
A50: 日期 | B50: 星期 | C50: 分类 | D50: 事项 | E50: 支出金额 | F50: 收入金额 | G50: 当笔净额 | H50: 支付方式 | I50: 备注
A51: 46181 | B51: 星期一 | C51: 餐饮 | D51: 早餐 | G51: =IF(AND(E51="",F51=""),"",F51-E51)
A52: 46181 | B52: 星期一 | C52: 餐饮 | D52: 中餐 | G52: =IF(AND(E52="",F52=""),"",F52-E52)
A53: 46181 | B53: 星期一 | C53: 餐饮 | D53: 晚餐 | G53: =IF(AND(E53="",F53=""),"",F53-E53)
A54: 46181 | B54: 星期一 | C54: 奶茶/咖啡 | D54: 奶茶/咖啡 | G54: =IF(AND(E54="",F54=""),"",F54-E54)
A55: 46181 | B55: 星期一 | C55: 其他 | D55: 其他 | G55: =IF(AND(E55="",F55=""),"",F55-E55)
A56: 46181 | B56: 星期一 | C56: 其他 | D56: 其他 | G56: =IF(AND(E56="",F56=""),"",F56-E56)
A57: 46182 | B57: 星期二 | C57: 餐饮 | D57: 早餐 | G57: =IF(AND(E57="",F57=""),"",F57-E57)
A58: 46182 | B58: 星期二 | C58: 餐饮 | D58: 中餐 | G58: =IF(AND(E58="",F58=""),"",F58-E58)
A59: 46182 | B59: 星期二 | C59: 餐饮 | D59: 晚餐 | G59: =IF(AND(E59="",F59=""),"",F59-E59)
A60: 46182 | B60: 星期二 | C60: 奶茶/咖啡 | D60: 奶茶/咖啡 | G60: =IF(AND(E60="",F60=""),"",F60-E60)
A61: 46182 | B61: 星期二 | C61: 其他 | D61: 其他 | G61: =IF(AND(E61="",F61=""),"",F61-E61)
A62: 46182 | B62: 星期二 | C62: 其他 | D62: 其他 | G62: =IF(AND(E62="",F62=""),"",F62-E62)
... A92: 46187 | B92: 星期日 | C92: 其他 | D92: 其他 | G92: =IF(AND(E92="",F92=""),"",F92-E92)
A93: 本周小计 | E93: =SUM(E51:E92) | F93: =SUM(F51:F92) | G93: =SUM(G51:G92)
A96: 2026年6月｜第三周（6月15日 - 6月21日）
A97: 日期 | B97: 星期 | C97: 分类 | D97: 事项 | E97: 支出金额 | F97: 收入金额 | G97: 当笔净额 | H97: 支付方式 | I97: 备注
A98: 46188 | B98: 星期一 | C98: 餐饮 | D98: 早餐 | G98: =IF(AND(E98="",F98=""),"",F98-E98)
A99: 46188 | B99: 星期一 | C99: 餐饮 | D99: 中餐 | G99: =IF(AND(E99="",F99=""),"",F99-E99)
A100: 46188 | B100: 星期一 | C100: 餐饮 | D100: 晚餐 | G100: =IF(AND(E100="",F100=""),"",F100-E100)
A101: 46188 | B101: 星期一 | C101: 奶茶/咖啡 | D101: 奶茶/咖啡 | G101: =IF(AND(E101="",F101=""),"",F101-E101)
A102: 46188 | B102: 星期一 | C102: 其他 | D102: 其他 | G102: =IF(AND(E102="",F102=""),"",F102-E102)
A103: 46188 | B103: 星期一 | C103: 其他 | D103: 其他 | G103: =IF(AND(E103="",F103=""),"",F103-E103)
A104: 46189 | B104: 星期二 | C104: 餐饮 | D104: 早餐 | G104: =IF(AND(E104="",F104=""),"",F104-E104)
A105: 46189 | B105: 星期二 | C105: 餐饮 | D105: 中餐 | G105: =IF(AND(E105="",F105=""),"",F105-E105)
A106: 46189 | B106: 星期二 | C106: 餐饮 | D106: 晚餐 | G106: =IF(AND(E106="",F106=""),"",F106-E106)
A107: 46189 | B107: 星期二 | C107: 奶茶/咖啡 | D107: 奶茶/咖啡 | G107: =IF(AND(E107="",F107=""),"",F107-E107)
A108: 46189 | B108: 星期二 | C108: 其他 | D108: 其他 | G108: =IF(AND(E108="",F108=""),"",F108-E108)
A109: 46189 | B109: 星期二 | C109: 其他 | D109: 其他 | G109: =IF(AND(E109="",F109=""),"",F109-E109)
... A139: 46194 | B139: 星期日 | C139: 其他 | D139: 其他 | G139: =IF(AND(E139="",F139=""),"",F139-E139)
A140: 本周小计 | E140: =SUM(E98:E139) | F140: =SUM(F98:F139) | G140: =SUM(G98:G139)
A143: 2026年6月｜第四周（6月22日 - 6月28日）
A144: 日期 | B144: 星期 | C144: 分类 | D144: 事项 | E144: 支出金额 | F144: 收入金额 | G144: 当笔净额 | H144: 支付方式 | I144: 备注
A145: 46195 | B145: 星期一 | C145: 餐饮 | D145: 早餐 | G145: =IF(AND(E145="",F145=""),"",F145-E145)
A146: 46195 | B146: 星期一 | C146: 餐饮 | D146: 中餐 | G146: =IF(AND(E146="",F146=""),"",F146-E146)
A147: 46195 | B147: 星期一 | C147: 餐饮 | D147: 晚餐 | G147: =IF(AND(E147="",F147=""),"",F147-E147)
A148: 46195 | B148: 星期一 | C148: 奶茶/咖啡 | D148: 奶茶/咖啡 | G148: =IF(AND(E148="",F148=""),"",F148-E148)
A149: 46195 | B149: 星期一 | C149: 其他 | D149: 其他 | G149: =IF(AND(E149="",F149=""),"",F149-E149)
A150: 46195 | B150: 星期一 | C150: 其他 | D150: 其他 | G150: =IF(AND(E150="",F150=""),"",F150-E150)
A151: 46196 | B151: 星期二 | C151: 餐饮 | D151: 早餐 | G151: =IF(AND(E151="",F151=""),"",F151-E151)
A152: 46196 | B152: 星期二 | C152: 餐饮 | D152: 中餐 | G152: =IF(AND(E152="",F152=""),"",F152-E152)
A153: 46196 | B153: 星期二 | C153: 餐饮 | D153: 晚餐 | G153: =IF(AND(E153="",F153=""),"",F153-E153)
A154: 46196 | B154: 星期二 | C154: 奶茶/咖啡 | D154: 奶茶/咖啡 | G154: =IF(AND(E154="",F154=""),"",F154-E154)
A155: 46196 | B155: 星期二 | C155: 其他 | D155: 其他 | G155: =IF(AND(E155="",F155=""),"",F155-E155)
A156: 46196 | B156: 星期二 | C156: 其他 | D156: 其他 | G156: =IF(AND(E156="",F156=""),"",F156-E156)
... A186: 46201 | B186: 星期日 | C186: 其他 | D186: 其他 | G186: =IF(AND(E186="",F186=""),"",F186-E186)
A187: 本周小计 | E187: =SUM(E145:E186) | F187: =SUM(F145:F186) | G187: =SUM(G145:G186)
A190: 2026年6月-7月｜第五周（6月29日 - 7月5日）
A191: 日期 | B191: 星期 | C191: 分类 | D191: 事项 | E191: 支出金额 | F191: 收入金额 | G191: 当笔净额 | H191: 支付方式 | I191: 备注
A192: 46202 | B192: 星期一 | C192: 餐饮 | D192: 早餐 | G192: =IF(AND(E192="",F192=""),"",F192-E192)
A193: 46202 | B193: 星期一 | C193: 餐饮 | D193: 中餐 | G193: =IF(AND(E193="",F193=""),"",F193-E193)
A194: 46202 | B194: 星期一 | C194: 餐饮 | D194: 晚餐 | G194: =IF(AND(E194="",F194=""),"",F194-E194)
A195: 46202 | B195: 星期一 | C195: 奶茶/咖啡 | D195: 奶茶/咖啡 | G195: =IF(AND(E195="",F195=""),"",F195-E195)
A196: 46202 | B196: 星期一 | C196: 其他 | D196: 其他 | G196: =IF(AND(E196="",F196=""),"",F196-E196)
A197: 46202 | B197: 星期一 | C197: 其他 | D197: 其他 | G197: =IF(AND(E197="",F197=""),"",F197-E197)
A198: 46203 | B198: 星期二 | C198: 餐饮 | D198: 早餐 | G198: =IF(AND(E198="",F198=""),"",F198-E198)
A199: 46203 | B199: 星期二 | C199: 餐饮 | D199: 中餐 | G199: =IF(AND(E199="",F199=""),"",F199-E199)
A200: 46203 | B200: 星期二 | C200: 餐饮 | D200: 晚餐 | G200: =IF(AND(E200="",F200=""),"",F200-E200)
A201: 46203 | B201: 星期二 | C201: 奶茶/咖啡 | D201: 奶茶/咖啡 | G201: =IF(AND(E201="",F201=""),"",F201-E201)
A202: 46203 | B202: 星期二 | C202: 其他 | D202: 其他 | G202: =IF(AND(E202="",F202=""),"",F202-E202)
A203: 46203 | B203: 星期二 | C203: 其他 | D203: 其他 | G203: =IF(AND(E203="",F203=""),"",F203-E203)
... A233: 46208 | B233: 星期日 | C233: 其他 | D233: 其他 | G233: =IF(AND(E233="",F233=""),"",F233-E233)
A234: 本周小计 | E234: =SUM(E192:E233) | F234: =SUM(F192:F233) | G234: =SUM(G192:G233)
A237: 2026年7月｜第一周（7月6日 - 7月12日）
A238: 日期 | B238: 星期 | C238: 分类 | D238: 事项 | E238: 支出金额 | F238: 收入金额 | G238: 当笔净额 | H238: 支付方式 | I238: 备注
A239: 46209 | B239: 星期一 | C239: 餐饮 | D239: 早餐 | G239: =IF(AND(E239="",F239=""),"",F239-E239)
A240: 46209 | B240: 星期一 | C240: 餐饮 | D240: 中餐 | G240: =IF(AND(E240="",F240=""),"",F240-E240)
A241: 46209 | B241: 星期一 | C241: 餐饮 | D241: 晚餐 | G241: =IF(AND(E241="",F241=""),"",F241-E241)
A242: 46209 | B242: 星期一 | C242: 奶茶/咖啡 | D242: 奶茶/咖啡 | G242: =IF(AND(E242="",F242=""),"",F242-E242)
A243: 46209 | B243: 星期一 | C243: 其他 | D243: 其他 | G243: =IF(AND(E243="",F243=""),"",F243-E243)
A244: 46209 | B244: 星期一 | C244: 其他 | D244: 其他 | G244: =IF(AND(E244="",F244=""),"",F244-E244)
A245: 46210 | B245: 星期二 | C245: 餐饮 | D245: 早餐 | G245: =IF(AND(E245="",F245=""),"",F245-E245)
A246: 46210 | B246: 星期二 | C246: 餐饮 | D246: 中餐 | G246: =IF(AND(E246="",F246=""),"",F246-E246)
A247: 46210 | B247: 星期二 | C247: 餐饮 | D247: 晚餐 | G247: =IF(AND(E247="",F247=""),"",F247-E247)
A248: 46210 | B248: 星期二 | C248: 奶茶/咖啡 | D248: 奶茶/咖啡 | G248: =IF(AND(E248="",F248=""),"",F248-E248)
A249: 46210 | B249: 星期二 | C249: 其他 | D249: 其他 | G249: =IF(AND(E249="",F249=""),"",F249-E249)
A250: 46210 | B250: 星期二 | C250: 其他 | D250: 其他 | G250: =IF(AND(E250="",F250=""),"",F250-E250)
... A280: 46215 | B280: 星期日 | C280: 其他 | D280: 其他 | G280: =IF(AND(E280="",F280=""),"",F280-E280)
A281: 本周小计 | E281: =SUM(E239:E280) | F281: =SUM(F239:F280) | G281: =SUM(G239:G280)
A284: 2026年7月｜第二周（7月13日 - 7月19日）
A285: 日期 | B285: 星期 | C285: 分类 | D285: 事项 | E285: 支出金额 | F285: 收入金额 | G285: 当笔净额 | H285: 支付方式 | I285: 备注
A286: 46216 | B286: 星期一 | C286: 餐饮 | D286: 早餐 | G286: =IF(AND(E286="",F286=""),"",F286-E286)
...

Sheet 按周汇总
A1: 按周汇总
A2: 周次 | B2: 起始日期 | C2: 结束日期 | D2: 支出合计 | E2: 收入合计 | F2: 本周净额 | G2: 累计余额 | H2: 备注
A3: 第1周 | B3: 46174 | C3: 46180 | D3: =SUM('流水记账'!E4:E45) | E3: =SUM('流水记账'!F4:F45) | F3: =E3-D3 | G3: ='按月汇总'!$B$2+SUM($F$3:F3)
A4: 第2周 | B4: 46181 | C4: 46187 | D4: =SUM('流水记账'!E51:E92) | E4: =SUM('流水记账'!F51:F92) | F4: =E4-D4 | G4: ='按月汇总'!$B$2+SUM($F$3:F4)
A5: 第3周 | B5: 46188 | C5: 46194 | D5: =SUM('流水记账'!E98:E139) | E5: =SUM('流水记账'!F98:F139) | F5: =E5-D5 | G5: ='按月汇总'!$B$2+SUM($F$3:F5)
A6: 第4周 | B6: 46195 | C6: 46201 | D6: =SUM('流水记账'!E145:E186) | E6: =SUM('流水记账'!F145:F186) | F6: =E6-D6 | G6: ='按月汇总'!$B$2+SUM($F$3:F6)
A7: 第5周 | B7: 46202 | C7: 46208 | D7: =SUM('流水记账'!E192:E233) | E7: =SUM('流水记账'!F192:F233) | F7: =E7-D7 | G7: ='按月汇总'!$B$2+SUM($F$3:F7)
A8: 第6周 | B8: 46209 | C8: 46215 | D8: =SUM('流水记账'!E239:E280) | E8: =SUM('流水记账'!F239:F280) | F8: =E8-D8 | G8: ='按月汇总'!$B$2+SUM($F$3:F8)
A9: 第7周 | B9: 46216 | C9: 46222 | D9: =SUM('流水记账'!E286:E327) | E9: =SUM('流水记账'!F286:F327) | F9: =E9-D9 | G9: ='按月汇总'!$B$2+SUM($F$3:F9)
A10: 第8周 | B10: 46223 | C10: 46229 | D10: =SUM('流水记账'!E333:E374) | E10: =SUM('流水记账'!F333:F374) | F10: =E10-D10 | G10: ='按月汇总'!$B$2+SUM($F$3:F10)
A11: 第9周 | B11: 46230 | C11: 46236 | D11: =SUM('流水记账'!E380:E421) | E11: =SUM('流水记账'!F380:F421) | F11: =E11-D11 | G11: ='按月汇总'!$B$2+SUM($F$3:F11)
A12: 第10周 | B12: 46237 | C12: 46243 | D12: =SUM('流水记账'!E427:E468) | E12: =SUM('流水记账'!F427:F468) | F12: =E12-D12 | G12: ='按月汇总'!$B$2+SUM($F$3:F12)
A13: 第11周 | B13: 46244 | C13: 46250 | D13: =SUM('流水记账'!E474:E515) | E13: =SUM('流水记账'!F474:F515) | F13: =E13-D13 | G13: ='按月汇总'!$B$2+SUM($F$3:F13)
A14: 第12周 | B14: 46251 | C14: 46257 | D14: =SUM('流水记账'!E521:E562) | E14: =SUM('流水记账'!F521:F562) | F14: =E14-D14 | G14: ='按月汇总'!$B$2+SUM($F$3:F14)
A15: 第13周 | B15: 46258 | C15: 46264 | D15: =SUM('流水记账'!E568:E609) | E15: =SUM('流水记账'!F568:F609) | F15: =E15-D15 | G15: ='按月汇总'!$B$2+SUM($F$3:F15)
A16: 第14周 | B16: 46265 | C16: 46271 | D16: =SUM('流水记账'!E615:E656) | E16: =SUM('流水记账'!F615:F656) | F16: =E16-D16 | G16: ='按月汇总'!$B$2+SUM($F$3:F16)
A17: 第15周 | B17: 46272 | C17: 46278 | D17: =SUM('流水记账'!E662:E703) | E17: =SUM('流水记账'!F662:F703) | F17: =E17-D17 | G17: ='按月汇总'!$B$2+SUM($F$3:F17)
A18: 第16周 | B18: 46279 | C18: 46285 | D18: =SUM('流水记账'!E709:E750) | E18: =SUM('流水记账'!F709:F750) | F18: =E18-D18 | G18: ='按月汇总'!$B$2+SUM($F$3:F18)
A19: 第17周 | B19: 46286 | C19: 46292 | D19: =SUM('流水记账'!E756:E797) | E19: =SUM('流水记账'!F756:F797) | F19: =E19-D19 | G19: ='按月汇总'!$B$2+SUM($F$3:F19)
A20: 第18周 | B20: 46293 | C20: 46299 | D20: =SUM('流水记账'!E803:E844) | E20: =SUM('流水记账'!F803:F844) | F20: =E20-D20 | G20: ='按月汇总'!$B$2+SUM($F$3:F20)
A21: 第19周 | B21: 46300 | C21: 46306 | D21: =SUM('流水记账'!E850:E891) | E21: =SUM('流水记账'!F850:F891) | F21: =E21-D21 | G21: ='按月汇总'!$B$2+SUM($F$3:F21)
A22: 第20周 | B22: 46307 | C22: 46313 | D22: =SUM('流水记账'!E897:E938) | E22: =SUM('流水记账'!F897:F938) | F22: =E22-D22 | G22: ='按月汇总'!$B$2+SUM($F$3:F22)
A23: 第21周 | B23: 46314 | C23: 46320 | D23: =SUM('流水记账'!E944:E985) | E23: =SUM('流水记账'!F944:F985) | F23: =E23-D23 | G23: ='按月汇总'!$B$2+SUM($F$3:F23)
A24: 第22周 | B24: 46321 | C24: 46327 | D24: =SUM('流水记账'!E991:E1032) | E24: =SUM('流水记账'!F991:F1032) | F24: =E24-D24 | G24: ='按月汇总'!$B$2+SUM($F$3:F24)
A25: 第23周 | B25: 46328 | C25: 46334 | D25: =SUM('流水记账'!E1038:E1079) | E25: =SUM('流水记账'!F1038:F1079) | F25: =E25-D25 | G25: ='按月汇总'!$B$2+SUM($F$3:F25)
A26: 第24周 | B26: 46335 | C26: 46341 | D26: =SUM('流水记账'!E1085:E1126) | E26: =SUM('流水记账'!F1085:F1126) | F26: =E26-D26 | G26: ='按月汇总'!$B$2+SUM($F$3:F26)
A27: 第25周 | B27: 46342 | C27: 46348 | D27: =SUM('流水记账'!E1132:E1173) | E27: =SUM('流水记账'!F1132:F1173) | F27: =E27-D27 | G27: ='按月汇总'!$B$2+SUM($F$3:F27)
A28: 第26周 | B28: 46349 | C28: 46355 | D28: =SUM('流水记账'!E1179:E1220) | E28: =SUM('流水记账'!F1179:F1220) | F28: =E28-D28 | G28: ='按月汇总'!$B$2+SUM($F$3:F28)
A29: 第27周 | B29: 46356 | C29: 46362 | D29: =SUM('流水记账'!E1226:E1267) | E29: =SUM('流水记账'!F1226:F1267) | F29: =E29-D29 | G29: ='按月汇总'!$B$2+SUM($F$3:F29)
A30: 第28周 | B30: 46363 | C30: 46369 | D30: =SUM('流水记账'!E1273:E1314) | E30: =SUM('流水记账'!F1273:F1314) | F30: =E30-D30 | G30: ='按月汇总'!$B$2+SUM($F$3:F30)
A31: 第29周 | B31: 46370 | C31: 46376 | D31: =SUM('流水记账'!E1320:E1361) | E31: =SUM('流水记账'!F1320:F1361) | F31: =E31-D31 | G31: ='按月汇总'!$B$2+SUM($F$3:F31)
A32: 第30周 | B32: 46377 | C32: 46383 | D32: =SUM('流水记账'!E1367:E1408) | E32: =SUM('流水记账'!F1367:F1408) | F32: =E32-D32 | G32: ='按月汇总'!$B$2+SUM($F$3:F32)
A33: 第31周 | B33: 46384 | C33: 46390 | D33: =SUM('流水记账'!E1414:E1455) | E33: =SUM('流水记账'!F1414:F1455) | F33: =E33-D33 | G33: ='按月汇总'!$B$2+SUM($F$3:F33)
A34: 第32周 | B34: 46391 | C34: 46397 | D34: =SUM('流水记账'!E1461:E1502) | E34: =SUM('流水记账'!F1461:F1502) | F34: =E34-D34 | G34: ='按月汇总'!$B$2+SUM($F$3:F34)
A35: 第33周 | B35: 46398 | C35: 46404 | D35: =SUM('流水记账'!E1508:E1549) | E35: =SUM('流水记账'!F1508:F1549) | F35: =E35-D35 | G35: ='按月汇总'!$B$2+SUM($F$3:F35)
A36: 第34周 | B36: 46405 | C36: 46411 | D36: =SUM('流水记账'!E1555:E1596) | E36: =SUM('流水记账'!F1555:F1596) | F36: =E36-D36 | G36: ='按月汇总'!$B$2+SUM($F$3:F36)
A37: 第35周 | B37: 46412 | C37: 46418 | D37: =SUM('流水记账'!E1602:E1643) | E37: =SUM('流水记账'!F1602:F1643) | F37: =E37-D37 | G37: ='按月汇总'!$B$2+SUM($F$3:F37)
A38: 第36周 | B38: 46419 | C38: 46425 | D38: =SUM('流水记账'!E1649:E1690) | E38: =SUM('流水记账'!F1649:F1690) | F38: =E38-D38 | G38: ='按月汇总'!$B$2+SUM($F$3:F38)
A39: 第37周 | B39: 46426 | C39: 46432 | D39: =SUM('流水记账'!E1696:E1737) | E39: =SUM('流水记账'!F1696:F1737) | F39: =E39-D39 | G39: ='按月汇总'!$B$2+SUM($F$3:F39)
A40: 第38周 | B40: 46433 | C40: 46439 | D40: =SUM('流水记账'!E1743:E1784) | E40: =SUM('流水记账'!F1743:F1784) | F40: =E40-D40 | G40: ='按月汇总'!$B$2+SUM($F$3:F40)
A41: 第39周 | B41: 46440 | C41: 46446 | D41: =SUM('流水记账'!E1790:E1831) | E41: =SUM('流水记账'!F1790:F1831) | F41: =E41-D41 | G41: ='按月汇总'!$B$2+SUM($F$3:F41)
A42: 第40周 | B42: 46447 | C42: 46453 | D42: =SUM('流水记账'!E1837:E1878) | E42: =SUM('流水记账'!F1837:F1878) | F42: =E42-D42 | G42: ='按月汇总'!$B$2+SUM($F$3:F42)
A43: 第41周 | B43: 46454 | C43: 46460 | D43: =SUM('流水记账'!E1884:E1925) | E43: =SUM('流水记账'!F1884:F1925) | F43: =E43-D43 | G43: ='按月汇总'!$B$2+SUM($F$3:F43)
A44: 第42周 | B44: 46461 | C44: 46467 | D44: =SUM('流水记账'!E1931:E1972) | E44: =SUM('流水记账'!F1931:F1972) | F44: =E44-D44 | G44: ='按月汇总'!$B$2+SUM($F$3:F44)
A45: 第43周 | B45: 46468 | C45: 46474 | D45: =SUM('流水记账'!E1978:E2019) | E45: =SUM('流水记账'!F1978:F2019) | F45: =E45-D45 | G45: ='按月汇总'!$B$2+SUM($F$3:F45)
A46: 第44周 | B46: 46475 | C46: 46481 | D46: =SUM('流水记账'!E2025:E2066) | E46: =SUM('流水记账'!F2025:F2066) | F46: =E46-D46 | G46: ='按月汇总'!$B$2+SUM($F$3:F46)
A47: 第45周 | B47: 46482 | C47: 46488 | D47: =SUM('流水记账'!E2072:E2113) | E47: =SUM('流水记账'!F2072:F2113) | F47: =E47-D47 | G47: ='按月汇总'!$B$2+SUM($F$3:F47)
A48: 第46周 | B48: 46489 | C48: 46495 | D48: =SUM('流水记账'!E2119:E2160) | E48: =SUM('流水记账'!F2119:F2160) | F48: =E48-D48 | G48: ='按月汇总'!$B$2+SUM($F$3:F48)
A49: 第47周 | B49: 46496 | C49: 46502 | D49: =SUM('流水记账'!E2166:E2207) | E49: =SUM('流水记账'!F2166:F2207) | F49: =E49-D49 | G49: ='按月汇总'!$B$2+SUM($F$3:F49)
A50: 第48周 | B50: 46503 | C50: 46509 | D50: =SUM('流水记账'!E2213:E2254) | E50: =SUM('流水记账'!F2213:F2254) | F50: =E50-D50 | G50: ='按月汇总'!$B$2+SUM($F$3:F50)
A51: 第49周 | B51: 46510 | C51: 46516 | D51: =SUM('流水记账'!E2260:E2301) | E51: =SUM('流水记账'!F2260:F2301) | F51: =E51-D51 | G51: ='按月汇总'!$B$2+SUM($F$3:F51)
A52: 第50周 | B52: 46517 | C52: 46523 | D52: =SUM('流水记账'!E2307:E2348) | E52: =SUM('流水记账'!F2307:F2348) | F52: =E52-D52 | G52: ='按月汇总'!$B$2+SUM($F$3:F52)
A53: 第51周 | B53: 46524 | C53: 46530 | D53: =SUM('流水记账'!E2354:E2395) | E53: =SUM('流水记账'!F2354:F2395) | F53: =E53-D53 | G53: ='按月汇总'!$B$2+SUM($F$3:F53)
A54: 第52周 | B54: 46531 | C54: 46537 | D54: =SUM('流水记账'!E2401:E2442) | E54: =SUM('流水记账'!F2401:F2442) | F54: =E54-D54 | G54: ='按月汇总'!$B$2+SUM($F$3:F54)
A55: 第53周 | B55: 46538 | C55: 46544 | D55: =SUM('流水记账'!E2448:E2489) | E55: =SUM('流水记账'!F2448:F2489) | F55: =E55-D55 | G55: ='按月汇总'!$B$2+SUM($F$3:F55)

Sheet 按月汇总
A1: 按月汇总
A2: 起始余额 | B2: 0 | C2: 总支出 | D2: =SUM(B6:B17) | E2: 总收入 | F2: =SUM(C6:C17)
A3: 总净额 | B3: =SUM(D6:D17) | C3: 当前余额 | D3: =B2+B3
A5: 月份 | B5: 支出合计 | C5: 收入合计 | D5: 本月净额 | E5: 累计余额 | F5: 备注
A6: 2026年6月 | B6: =SUMIFS('流水记账'!$E:$E,'流水记账'!$A:$A,">="&DATE(2026,6,1),'流水记账'!$A:$A,"<"&DATE(2026,7,1)) | C6: =SUMIFS('流水记账'!$F:$F,'流水记账'!$A:$A,">="&DATE(2026,6,1),'流水记账'!$A:$A,"<"&DATE(2026,7,1)) | D6: =C6-B6 | E6: =$B$2+SUM($D$6:D6)
A7: 2026年7月 | B7: =SUMIFS('流水记账'!$E:$E,'流水记账'!$A:$A,">="&DATE(2026,7,1),'流水记账'!$A:$A,"<"&DATE(2026,8,1)) | C7: =SUMIFS('流水记账'!$F:$F,'流水记账'!$A:$A,">="&DATE(2026,7,1),'流水记账'!$A:$A,"<"&DATE(2026,8,1)) | D7: =C7-B7 | E7: =$B$2+SUM($D$6:D7)
A8: 2026年8月 | B8: =SUMIFS('流水记账'!$E:$E,'流水记账'!$A:$A,">="&DATE(2026,8,1),'流水记账'!$A:$A,"<"&DATE(2026,9,1)) | C8: =SUMIFS('流水记账'!$F:$F,'流水记账'!$A:$A,">="&DATE(2026,8,1),'流水记账'!$A:$A,"<"&DATE(2026,9,1)) | D8: =C8-B8 | E8: =$B$2+SUM($D$6:D8)
A9: 2026年9月 | B9: =SUMIFS('流水记账'!$E:$E,'流水记账'!$A:$A,">="&DATE(2026,9,1),'流水记账'!$A:$A,"<"&DATE(2026,10,1)) | C9: =SUMIFS('流水记账'!$F:$F,'流水记账'!$A:$A,">="&DATE(2026,9,1),'流水记账'!$A:$A,"<"&DATE(2026,10,1)) | D9: =C9-B9 | E9: =$B$2+SUM($D$6:D9)
A10: 2026年10月 | B10: =SUMIFS('流水记账'!$E:$E,'流水记账'!$A:$A,">="&DATE(2026,10,1),'流水记账'!$A:$A,"<"&DATE(2026,11,1)) | C10: =SUMIFS('流水记账'!$F:$F,'流水记账'!$A:$A,">="&DATE(2026,10,1),'流水记账'!$A:$A,"<"&DATE(2026,11,1)) | D10: =C10-B10 | E10: =$B$2+SUM($D$6:D10)
A11: 2026年11月 | B11: =SUMIFS('流水记账'!$E:$E,'流水记账'!$A:$A,">="&DATE(2026,11,1),'流水记账'!$A:$A,"<"&DATE(2026,12,1)) | C11: =SUMIFS('流水记账'!$F:$F,'流水记账'!$A:$A,">="&DATE(2026,11,1),'流水记账'!$A:$A,"<"&DATE(2026,12,1)) | D11: =C11-B11 | E11: =$B$2+SUM($D$6:D11)
A12: 2026年12月 | B12: =SUMIFS('流水记账'!$E:$E,'流水记账'!$A:$A,">="&DATE(2026,12,1),'流水记账'!$A:$A,"<"&DATE(2027,1,1)) | C12: =SUMIFS('流水记账'!$F:$F,'流水记账'!$A:$A,">="&DATE(2026,12,1),'流水记账'!$A:$A,"<"&DATE(2027,1,1)) | D12: =C12-B12 | E12: =$B$2+SUM($D$6:D12)
A13: 2027年1月 | B13: =SUMIFS('流水记账'!$E:$E,'流水记账'!$A:$A,">="&DATE(2027,1,1),'流水记账'!$A:$A,"<"&DATE(2027,2,1)) | C13: =SUMIFS('流水记账'!$F:$F,'流水记账'!$A:$A,">="&DATE(2027,1,1),'流水记账'!$A:$A,"<"&DATE(2027,2,1)) | D13: =C13-B13 | E13: =$B$2+SUM($D$6:D13)
A14: 2027年2月 | B14: =SUMIFS('流水记账'!$E:$E,'流水记账'!$A:$A,">="&DATE(2027,2,1),'流水记账'!$A:$A,"<"&DATE(2027,3,1)) | C14: =SUMIFS('流水记账'!$F:$F,'流水记账'!$A:$A,">="&DATE(2027,2,1),'流水记账'!$A:$A,"<"&DATE(2027,3,1)) | D14: =C14-B14 | E14: =$B$2+SUM($D$6:D14)
A15: 2027年3月 | B15: =SUMIFS('流水记账'!$E:$E,'流水记账'!$A:$A,">="&DATE(2027,3,1),'流水记账'!$A:$A,"<"&DATE(2027,4,1)) | C15: =SUMIFS('流水记账'!$F:$F,'流水记账'!$A:$A,">="&DATE(2027,3,1),'流水记账'!$A:$A,"<"&DATE(2027,4,1)) | D15: =C15-B15 | E15: =$B$2+SUM($D$6:D15)
A16: 2027年4月 | B16: =SUMIFS('流水记账'!$E:$E,'流水记账'!$A:$A,">="&DATE(2027,4,1),'流水记账'!$A:$A,"<"&DATE(2027,5,1)) | C16: =SUMIFS('流水记账'!$F:$F,'流水记账'!$A:$A,">="&DATE(2027,4,1),'流水记账'!$A:$A,"<"&DATE(2027,5,1)) | D16: =C16-B16 | E16: =$B$2+SUM($D$6:D16)
A17: 2027年5月 | B17: =SUMIFS('流水记账'!$E:$E,'流水记账'!$A:$A,">="&DATE(2027,5,1),'流水记账'!$A:$A,"<"&DATE(2027,6,1)) | C17: =SUMIFS('流水记账'!$F:$F,'流水记账'!$A:$A,">="&DATE(2027,5,1),'流水记账'!$A:$A,"<"&DATE(2027,6,1)) | D17: =C17-B17 | E17: =$B$2+SUM($D$6:D17)

Sheet 选项设置
A1: 分类 | B1: 支付方式 | C1: 事项
A2: 餐饮 | B2: 微信 | C2: 奶茶/咖啡
A3: 奶茶/咖啡 | B3: 支付宝 | C3: 交通
A4: 交通 | B4: 银行卡 | C4: 购物
A5: 购物 | B5: 现金 | C5: 娱乐
A6: 娱乐 | B6: 信用卡 | C6: 生活用品
A7: 生活用品 | B7: 其他 | C7: 旅行
A8: 旅行 | C8: 医疗
A9: 医疗 | C9: 人情/礼物
A10: 人情/礼物 | C10: 房租/固定支出
A11: 房租/固定支出 | C11: 其他
A12: 家庭支出 | C12: 早餐
A13: 其他 | C13: 中餐
C14: 晚餐
